Workbook
Name AQUI_COLOQUE_LAS_FOTOS: FORMULARIO_GARANTIA!$C$79
Name CELDA_BOLETA_FACTURA: FORMULARIO_GARANTIA!$G$38
Name CELDA_CIUDAD_CLIENTE: FORMULARIO_GARANTIA!$D$39
Name CELDA_DIRECCION_CLIENTE: FORMULARIO_GARANTIA!$D$38
Name CELDA_DISTRIBUIDOR: FORMULARIO_GARANTIA!$G$12
Name CELDA_DISTRIBUIDOR_FILA2: FORMULARIO_GARANTIA!$E$12
Name CELDA_DISTRIBUIDOR_FILA3: FORMULARIO_GARANTIA!#REF!
Name CELDA_F_AUTORIZACION: FORMULARIO_GARANTIA!$G$71
Name CELDA_F_COMPRA: FORMULARIO_GARANTIA!$G$37
Name CELDA_F_DE_EMISION_STA: FORMULARIO_GARANTIA!$G$72
Name CELDA_F_RECEPCION: FORMULARIO_GARANTIA!$G$36
Name CELDA_FALLA: FORMULARIO_GARANTIA!$D$57
Name CELDA_FALTAN_DATOS: FORMULARIO_GARANTIA!$C$75
Name CELDA_FIRMA_CLIENTE: FORMULARIO_GARANTIA!$G$40
Name CELDA_FORMULARIO_VALIDO_O_NO_VALIDO: FORMULARIO_GARANTIA!$D$2
Name CELDA_INFORME_TECNICO: FORMULARIO_GARANTIA!$D$58
Name CELDA_MODELO: FORMULARIO_GARANTIA!$D$44
Name CELDA_NOM_COMERCIAL_DEL_SERVICIO_TECNICO: FORMULARIO_GARANTIA!$G$11
Name CELDA_NOMBRE_CLIENTE: FORMULARIO_GARANTIA!$D$37
Name CELDA_NOMBRE_DEL_SERVICO_TECNICO: FORMULARIO_GARANTIA!$D$30
Name CELDA_NOMBRE_MPE: FORMULARIO_GARANTIA!$D$70
Name CELDA_NUMERO_MPE_DE_AUTORIZACION: FORMULARIO_GARANTIA!$D$27
Name CELDA_OT: FORMULARIO_GARANTIA!$G$27
Name CELDA_PRIMERA_LINEA_COMENTARIO_MPE: FORMULARIO_GARANTIA!$D$72
Name CELDA_RUC_CLIENTE: FORMULARIO_GARANTIA!$D$36
Name CELDA_RUC_DEL_SERVICIO_TECNICO: FORMULARIO_GARANTIA!$D$29
Name CELDA_SEGUNDA_LINEA_COMENTARIO_MPE: FORMULARIO_GARANTIA!$C$73
Name CELDA_SERIE: FORMULARIO_GARANTIA!$G$44
Name CELDA_TECNICO_DEL_STA: FORMULARIO_GARANTIA!$G$73
Name CELDA_TELEFONO_CLIENTE: FORMULARIO_GARANTIA!$D$40
Name CELDA_TERCERA_LINEA_COMENTARIO_MPE: FORMULARIO_GARANTIA!$C$74
Name CELDA_TOTAL_CODIGOS: FORMULARIO_GARANTIA!$C$55
Name ELIJA_MANO_D_OBRA: FORMULARIO_GARANTIA!$G$75
Name ELIJA_UN_CODIGO_D_FALLA: FORMULARIO_GARANTIA!$F$8
Name ELIJA_UNA_CATEGORIA_D_FALLA: FORMULARIO_GARANTIA!$G$60
Name RANGO_SUMA_CLIENTE: FORMULARIO_GARANTIA!$E$36:$E$41
Name RANGO_SUMA_DATOS_DOC: FORMULARIO_GARANTIA!$H$37:$H$40
Name RANGO_SUMA_FALLA_Y_DEBIDOA: FORMULARIO_GARANTIA!$E$57:$E$58
Name RANGO_SUMA_MODELO: FORMULARIO_GARANTIA!$E$44
Name RANGO_SUMA_OT: FORMULARIO_GARANTIA!$H$27
Name RANGO_SUMA_SERIE: FORMULARIO_GARANTIA!$H$44
Name RANGO_SUMA_ST_STMPE: FORMULARIO_GARANTIA!$E$29:$E$30
Name RANGO_SUMA_SUSTENTO_COMENTARIO: FORMULARIO_GARANTIA!$H$61
Name RG_CODIGOS: FORMULARIO_GARANTIA!$C$47:$C$54
Name RG_CODIGOS_DESCRIPCIONES_CANTIDADES: FORMULARIO_GARANTIA!$C$47:$E$54
Name RG_DATOS_RESUMEN: FORMULARIO_GARANTIA!$D$1:$D$24
Name RG_MANO_D_OBRA: FORMULARIO_GARANTIA!$G$15:$G$18
Name SUSTENTO_COMENTARIO_LINEA1: FORMULARIO_GARANTIA!$C$61
Name SUSTENTO_COMENTARIO_LINEA2: FORMULARIO_GARANTIA!$C$62
Name SUSTENTO_COMENTARIO_LINEA3: FORMULARIO_GARANTIA!$C$63
Name SUSTENTO_COMENTARIO_LINEA4: FORMULARIO_GARANTIA!$C$64
Name SUSTENTO_COMENTARIO_LINEA5: FORMULARIO_GARANTIA!$C$65
Name SUSTENTO_COMENTARIO_LINEA6: FORMULARIO_GARANTIA!$C$66
Name SUSTENTO_COMENTARIO_LINEA7: FORMULARIO_GARANTIA!$C$67
Name SUSTENTO_COMENTARIO_LINEA8: FORMULARIO_GARANTIA!$C$68

Sheet FORMULARIO_GARANTIA
C1: AUTORIZACION Nº : | D1: =IF(CELDA_NUMERO_MPE_DE_AUTORIZACION="","Vacio",CELDA_NUMERO_MPE_DE_AUTORIZACION) -> MPE26-425 | E1: ENVIOS | G1: "Envie el Formulario para evaluacion. La respuesta se dara por correo" | H1: .
C2: Ruc Servicio Tecnico : | D2: =IF(CELDA_RUC_DEL_SERVICIO_TECNICO="","Vacio",CELDA_RUC_DEL_SERVICIO_TECNICO) -> 10295867782 | E2: L | F2: Para la observacion | G2: Para valuar el Formulario enviar a: serviciotecnicompe@makita.pe | H2: .
C3: Nom. Servicio Tecnico : | D3: =IF(CELDA_NOMBRE_DEL_SERVICO_TECNICO="","Vacio",CELDA_NOMBRE_DEL_SERVICO_TECNICO) -> QUISPE PARI FREDY | E3: P | F3: Para la observacion | G3: Formulario rechazado: Esta incompleta la informacion de las celdas | H3: .
C4: Ruc : | D4: =IF(CELDA_RUC_CLIENTE="","Vacio",CELDA_RUC_CLIENTE) -> 20519999324 | E4: S | F4: Para la casilla de verif | G4: =IF(G5=TRUE,"NOTA: ENTREGAR LOS RPTOS AL STMPE"," ") -> NOTA: ENTREGAR LOS RPTOS AL STMPE
C5: Nombre : | D5: =IF(CELDA_NOMBRE_CLIENTE="","Vacio",CELDA_NOMBRE_CLIENTE) -> Contratistas Generales Sisten SRL | F5: Para la casilla de verif | G5: TRUE
C6: Ciudad : | D6: =IF(CELDA_CIUDAD_CLIENTE="","Vacio",CELDA_CIUDAD_CLIENTE) -> MOQUEGUA-ILO-ILO | E6: DESPACHO POR ALMACEN (LIMA) | G6: "Envie el Formulario a Makita. La respuesta se dara por correo, con el N° de MPE" | H6: .
C7: Ot : | D7: =IF(CELDA_OT="","Vacio",CELDA_OT) -> 612 | E7: DESPACHO POR COURIER (PROVINCIA) | F7: CODIGO PRINCIPAL DE LA FALLA
C8: F. Recepcion : | D8: =IF(CELDA_F_RECEPCION="","Vacio",CELDA_F_RECEPCION) -> 46213 | E8: ENTREGAR A STMPE (HTA EN STMPE)
C9: F. Compra : | D9: =IF(CELDA_F_COMPRA="","Vacio",CELDA_F_COMPRA) -> 46209 | E9: 1 | F9: Tecnico del STA : | G9: equivale fecha de aprobacion
C10: Boleta/Fact : | D10: =IF(CELDA_BOLETA_FACTURA="","Vacio",CELDA_BOLETA_FACTURA) -> E001-3514 | E10: =IF(E9=1,E6,IF(E9=2,E7,IF(E9=3,E8,""))) -> DESPACHO POR ALMACEN (LIMA) | F10: F. de Emision STA : | G10: equivale fecha de rechazao
C11: Distribuidor : | D11: =IF(CELDA_DISTRIBUIDOR="","Vacio",CELDA_DISTRIBUIDOR) -> Vacio | F11: Nombre comercial :
C12: Modelo : | D12: =IF(CELDA_MODELO="","Vacio",CELDA_MODELO) -> DGA452 | F12: Distribuidor : | H12: =IF(CELDA_NOM_COMERCIAL_DEL_SERVICIO_TECNICO="",1,0) -> 1
C13: Serie : | D13: =IF(CELDA_SERIE="","Vacio",CELDA_SERIE) -> 2092084Y | F13: NOMBRE STMPE | G13: LISTA DE MANO DE OBRA
C14: Falla : | D14: =IF(CELDA_FALLA="","Vacio",CELDA_FALLA) -> BATERIA NO CARGA | F14: Richard Janampa | G14: PARA LOS STA
C15: Informe Tecnico de Falla : | D15: =IF(CELDA_INFORME_TECNICO="","Vacio",CELDA_INFORME_TECNICO) -> FALLA INTERNA DE FABRICA | F15: Gerardo Gabriel | G15: 0
C16: Sustento/Comentario : | D16: =CONCATENATE(SUSTENTO_COMENTARIO_LINEA1," ",SUSTENTO_COMENTARIO_LINEA2," ",SUSTENTO_COMENTARIO_LINEA3," ",SUSTENTO_COMENTARIO_LINEA4," ",SUSTENTO_COMENTARIO_LINEA5," ",SUSTENTO_COMENTARIO_LINEA6," ",SUSTENTO_COMENTARIO_LINEA7," ",SUSTENTO_COMENTARIO_LINEA8) -> SEGÚN EL ANALIZADOR, SE ENCONTRÓ QUE UNA DE LAS BATERÍAS NO PRESENTA SOBRECARGA, MIENTRAS QUE LA OTRA SÍ, CON UN VALOR DEL 15%. ASIMISMO, LAS BATERÍAS REGISTRAN POCAS CARGAS, LO QUE DEMUESTRA QUE EN SU HISTORIAL NO HAN SUFRIDO SOBRECARGAS CONSTANTES NI SOBREDESCARGAS. PROCEDE GARANTIA | E16: . | F16: Juan Pablo Franco | G16: 28
C17: Categoria Falla : tipos de G. | D17: =ELIJA_UNA_CATEGORIA_D_FALLA -> 0 | E17: NG | F17: No es falla de fabrica | G17: 40
C18: Codigo de Falla : sin usar | D18: =ELIJA_UN_CODIGO_D_FALLA -> 0 | E18: GC | F18: Garantia comercial | G18: 65
C19: Fecha de Aprobacion | D19: =IF(CELDA_TECNICO_DEL_STA="", "Vacio",CELDA_TECNICO_DEL_STA) -> Vacio | E19: GM | F19: Garantia de equipo
C20: F. de Rechazo | D20: =IF(CELDA_F_DE_EMISION_STA="","Vacio",CELDA_F_DE_EMISION_STA) -> Vacio | E20: EdG | F20: Extension de garantia
C21: Nombre MPE : | D21: =IF(CELDA_NOMBRE_MPE="","Vacio",CELDA_NOMBRE_MPE) -> Gerardo Gabriel | E21: GdD | F21: Garantia de Retail
C22: Comentario MPE : | D22: =IF(CELDA_FALTAN_DATOS=G3,CELDA_FALTAN_DATOS,CONCATENATE(CELDA_PRIMERA_LINEA_COMENTARIO_MPE," ",CELDA_SEGUNDA_LINEA_COMENTARIO_MPE," ",CELDA_TERCERA_LINEA_COMENTARIO_MPE)) -> Procede Garantia | E22: MdO | F22: solo mano de obra | G22: Procede Garantia | H22: =IF(CELDA_DISTRIBUIDOR="",1,0) -> 1
C23: Fecha de Revision | D23: =IF(CELDA_F_AUTORIZACION="","Vacio",CELDA_F_AUTORIZACION) -> 46223 | E23: GdR | F23: Garantia de repuestos | G23: Procede Garantia - Solo Pago de Mano de obra
C24: Mano de Obra | D24: =IF(ELIJA_MANO_D_OBRA="","Vacio",ELIJA_MANO_D_OBRA) -> 28 | E24: GdA | F24: Garantia de accesorios | G24: No Procede Garantia
A25: Columna1 | B25: Columna1 | C25: FORMULARIO DE RECLAMACION DE GARANTIA 2026
C27: AUTORIZACION Nº: | D27: MPE26-425 | F27: Nº Gart / Ot. STA: | G27: 612 | H27: =IF(CELDA_OT="",1,0) -> 0
C29: Ruc. del STA : | D29: 10295867782 | E29: =IF(CELDA_RUC_DEL_SERVICIO_TECNICO="",1,0) -> 0
C30: Nombre del STA : | D30: =IFERROR(VLOOKUP(CELDA_RUC_DEL_SERVICIO_TECNICO,BASE_STA!B10:O200,2,FALSE),"") -> QUISPE PARI FREDY | E30: =IF(CELDA_NOMBRE_DEL_SERVICO_TECNICO="",1,0) -> 0
C31: Direccion STA : | D31: =CONCATENATE(IFERROR(VLOOKUP(CELDA_RUC_DEL_SERVICIO_TECNICO,BASE_STA!B10:O200,6,FALSE),"")) -> AV. JESUS 100 C.C.DIVINO JESUS INT. 16, AREQUIPA | E31: .
C32: Reg. Prov. Dist. : | D32: =IF(CELDA_RUC_DEL_SERVICIO_TECNICO="","",CONCATENATE("",IFERROR(VLOOKUP(CELDA_RUC_DEL_SERVICIO_TECNICO,BASE_STA!B10:O200,3,FALSE),"")," - ",IFERROR(VLOOKUP(CELDA_RUC_DEL_SERVICIO_TECNICO,BASE_STA!B10:O200,4,FALSE),"")," - ",IFERROR(VLOOKUP(CELDA_RUC_DEL_SERVICIO_TECNICO,BASE_STA!B10:O200,5,FALSE),""),"")) -> AREQUIPA - AREQUIPA - AREQUIPA
C33: Contacto : | D33: =CONCATENATE(IFERROR(VLOOKUP(CELDA_RUC_DEL_SERVICIO_TECNICO,BASE_STA!B10:O100,9,FALSE),"")) -> FREDY QUISPE
C34: Telefonos : | D34: =CONCATENATE(IFERROR(VLOOKUP(CELDA_RUC_DEL_SERVICIO_TECNICO,BASE_STA!B10:O200,8,FALSE),"")) -> 935829261 / 959613059
C36: Ruc/Dni del Cliente : | D36: 20519999324 | E36: =IF(CELDA_RUC_CLIENTE="",1,0) -> 0 | F36: Fecha Recepción : | G36: 46213 | H36: =IF(CELDA_F_RECEPCION="",1,0) -> 0
C37: Nombre del Cliente : | D37: Contratistas Generales Sisten SRL | E37: =IF(CELDA_NOMBRE_CLIENTE="",1,0) -> 0 | F37: Fecha Compra : | G37: 46209 | H37: =IF(CELDA_F_COMPRA="",1,0) -> 0
C38: Dirección : | D38: A.H. NUEVA VICTORIA MZA. 26 LOTE. 19 | E38: =IF(CELDA_DIRECCION_CLIENTE="",1,0) -> 0 | F38: Boleta/Factura : | G38: E001-3514 | H38: =IF(CELDA_BOLETA_FACTURA="",1,0) -> 0
C39: Ciudad : | D39: MOQUEGUA-ILO-ILO | E39: =IF(CELDA_CIUDAD_CLIENTE="",1,0) -> 0
C40: Teléfono : | D40: 912421367 | E40: =IF(CELDA_TELEFONO_CLIENTE="",1,0) -> 0 | F40: Firma :
H41: .
H42: .
C44: Modelo : | D44: DGA452 | E44: =IF(CELDA_MODELO="",1,0) -> 0 | F44: Serie Nº : | G44: 2092084Y | H44: =IF(CELDA_SERIE="",1,0) -> 0
C46: Código | D46: Descripcion | E46: Cant. | F46: .
C47: NO BORRAR
C48: 632G12-3 | D48: BATERIA 18V LXT 3.0 Ah | E48: 2 | F48: stock
B55: Columna1 | C55: =CONCATENATE("[TOTAL DE CODIGOS]: ",SUM(COUNTA(RG_CODIGOS)-1)) -> [TOTAL DE CODIGOS]: 1
C56: INFORME TECNICO DEL PROBLEMA
C57: Cual es el Problema : | D57: BATERIA NO CARGA | E57: =IF(CELDA_FALLA="",1,0) -> 0
C58: A causa de que : | D58: FALLA INTERNA DE FABRICA | E58: =IF(CELDA_INFORME_TECNICO="",1,0) -> 0
C60: Sustente o comente, que el problema encontrado, es por fabricacion y no por un mal uso de la herramienta:
C61: SEGÚN EL ANALIZADOR, SE ENCONTRÓ QUE UNA DE LAS BATERÍAS NO PRESENTA SOBRECARGA, MIENTRAS QUE LA OTRA SÍ, CON UN VALOR DEL 15%. ASIMISMO, LAS BATERÍAS REGISTRAN POCAS CARGAS, LO QUE DEMUESTRA QUE EN SU HISTORIAL NO HAN SUFRIDO SOBRECARGAS CONSTANTES NI SOBREDESCARGAS. PROCEDE GARANTIA | H61: =IF(SUSTENTO_COMENTARIO_LINEA1="",1,0) -> 0
C70: NOMBRE MPE : | D70: Gerardo Gabriel | F70: V.B. | G70: FECHA:
F71: Revision : | G71: 46223
C72: =CONCATENATE("Comentario MPE ", "(",IF(E10=E6,"L",IF(E10=E7,"P",IF(E10=E8,"S",""))),"):") -> Comentario MPE (L): | F72: Rechazo :
C73: Procede Garantia | F73: Aprobacion :
C75: =IF(SUM(RANGO_SUMA_CLIENTE,RANGO_SUMA_DATOS_DOC,RANGO_SUMA_FALLA_Y_DEBIDOA,RANGO_SUMA_MODELO,RANGO_SUMA_OT,RANGO_SUMA_SERIE,RANGO_SUMA_ST_STMPE,RANGO_SUMA_SUSTENTO_COMENTARIO)<>0,G3,G2) -> Para valuar el Formulario enviar a: serviciotecnicompe@makita.pe | F75: Mano de obra : | G75: 28
C77: NOTA: Todos los formularios que entraran para evaluacion, deveran ser enviados al correo de: serviciotecnicompe@makita.pe
C79: 1 - Foto del numero de serie (Legible) , y Foto general de la maquina, de la cara donde esta la placa
C98: 2 - Foto de los repuestos solicitados con la comprobacion de la falla.
C101: 3 - Foto que compruebe que es nueva la maquina o con poco uso, por ejemplo: La grasa, Carbones, Engranajes, Colector u otro.
C116: 4- Comprobante de venta: (Factura, boleta, tiqueck...)
C118: Ponga aquí para Retail: Primero la Factura, y Debajo la OST o la Solicitud de Reclamo.
C119: (Nota: Solo entraran en evaluacion los formularios de garantia, para las maquinas vendidas a cliente final, y no para las de exhibicion*)
C122: Ponga aquí para Garantia de repuestos: Primero Comprobante de la reparacion (Factura, boleta, tiqueck...), y Debajo la Guia de recepcion de la maquina
C123: (Nota: En el comprobante tiene que estar la siguiente informacion: el numero de serie de la placa y los codigos de los repuestos que habian fallado)

Sheet BASE_STA
B7: NOTA: NO ORDENA. LAS COLUMNAS DE ENCABEZADO ROJO SON LOS QUE VAN A USARSE EN EL FORMULARIO DE GARANTIA. ACTUALIZADO EL 30-12-2024
B10: RUC | C10: RAZON S. | D10: REGION | E10: PROVINCIA | F10: DISTRITO | G10: DIRECCION | H10: NOMBRE COMERCIAL | I10: TELEFONO | J10: CONTACTO | K10: CORREO 1 | L10: CORREO 2 | M10: ESPECIALIDAD | N10: DIST/STAM | O10: ESTADO | P10: F.CREACION | S10: FICHA RUC | T10: BANCO | U10: Nº DE CUENTA | V10: CCI | X10: REFERENCIA | Y10: COORDENADAS
A11: 1 | B11: 10024216671 | C11: MSA PROMOTOR INDUSTRIAL Y COMERCIAL MOISES CAYO PACHAURI | D11: PUNO | E11: SAN ROMAN | F11: JULIACA | G11: JR. SAN MARTIN 550, JULIACA | H11: MOISES CAYO PACHAURI | I11: 965606002 | J11: MAIDA LUPO / MOISES CAYO | K11: moises_cayo_pachauri@hotmail.com | M11: ELECTRICO | N11: STAM | O11: EVALUACION | P11: FY111 | S11: SI | T11: BCP | U11: 405-19724174-0-95 | X11: (REF. AL COSTADO DE CAJA HUANCAYO, A MEDIA CDRA. DE LA COMISARIA DE JULIACA) | Y11: -15.493178, -70.128491
A12: 2 | B12: 10107235677 | C12: NOLAZCO FELIX JOSE LUIS | D12: LIMA | E12: LIMA | F12: ATE | G12: AV. CARRETERA CENTRAL KM16.50, ATE | H12: NOLAZCO FELIX JOSE LUIS | I12: 981310248 / 917324463 | J12: ROSA CRIOLLO | K12: st.nolazco@gmail.com | M12: ELECTRICO | N12: STAM | O12: VIGENTE | P12: FY111 | S12: SI | T12: BCP | U12: 194-24049062-0-80 | V12: 00219412404906208095 | X12: (REF. A UNA CDRA. ANTES DE LLEGAR AL PARADERO HUAYCAN, ATE) | Y12: -12.001203, -76.839918
A13: 3 | B13: 10107310067 | C13: ORTIZ RAMIREZ JORGE ANIBAL | D13: LAMBAYEQUE | E13: CHICLAYO | F13: CHICLAYO | G13: CAL. MANUEL SUAREZ 479, URB. SAN LUIS, CHICLAYO | H13: TECNICENTRO CHICLAYO | I13: 074-222207 / 945968360 | J13: YASURI GONZALES | K13: ventas.chiclayo@tecnicentroperu.pe | M13: ELECTRICO+COMBUSTION | N13: DIST+STAM | O13: VIGENTE | P13: FY111 | S13: SI | T13: BCP | U13: 305-2187272-0-63 | X13: (REF. ALTURRA DE LA CDRA. 15 DE LUIS GONZALES) | Y13: -6.7638065,-79.8413813
A14: 4 | B14: 10165337935 | C14: CASTAÑEDA SALDAÑA WILSON | D14: AYACUCHO | E14: LUCANAS | F14: SANCOS | G14: PJE. SOTRAMI S/N - C.P. SANTA FILOMENA, SANCOS | H14: CASTAÑEDA SALDAÑA WILSON (MAKITA CENTER) | I14: 992869440 | J14: WILSON CASTAÑEDA | K14: wicasalda@hotmail.com | M14: ELECTRICO | N14: STAM MINERIA | O14: VIGENTE | P14: FY111 | S14: SI | T14: BCP | U14: 440-96260835089 | X14: (FALTA INFO) | Y14: -15.359473, -74.274456
A15: 5 | B15: 10295867782 | C15: QUISPE PARI FREDY | D15: AREQUIPA | E15: AREQUIPA | F15: AREQUIPA | G15: AV. JESUS 100 C.C.DIVINO JESUS INT. 16, AREQUIPA | H15: SERVICIO TECNICO "EL CHARLY" | I15: 935829261 / 959613059 | J15: FREDY QUISPE | K15: fchquispe@hotmail.com | M15: ELECTRICO+COMBUSTION | N15: STAM | O15: VIGENTE | P15: FY111 | S15: SI | T15: BCP | U15: 215-25572892-0-99 | X15: (FALTA INFO) | Y15: -16.4032578,-71.5165465
A16: 6 | B16: 10404097372 | C16: YOVANA ZUÑIGA QUISPE | D16: DTP APURIMAC | E16: ANDAHUAYLAS | F16: ANDAHUAYLAS | G16: AV. LAZARP CARRILLO 287, ANDAHUAYLAS | H16: MAQUINARIAS Y EQUIPOS ZUÑIGA | I16: 983657676 / 998608850 | J16: YOVANA ZUÑIGA | K16: zenobio.3007@gamil.com | M16: ELECTRICO | N16: STAM | O16: EVALUACION | P16: FY111 | S16: SI | T16: BCP | U16: 205-38376605-0-33 | V16: 002-205-138376605033-39 | X16: (FALTA INFO) | Y16: -13.659619059703525, -73.39068265258378
A17: 7 | B17: 10407513407 | C17: PAUCAR SANTIAGO WILDER | D17: JUNIN | E17: HUANCAYO | F17: HUANCAYO | G17: JR. LORETO 682, HUANCAYO | H17: PS INGENIEROS | I17: 964468221 | J17: WILDER PAUCAR | K17: ps.ingeniero@hotmail.com; servitec.ingenieros@hotmail.com | L17: servitec.ingenieros@hotmail.com | M17: ELECTRICO+COMBUSTION | N17: STAM | O17: EVALUACION | P17: FY111 | S17: SI | T17: SCOTIABANK | U17: 6740353864 | V17: 00967420674035386435 | X17: (REF. ENTRE EL JR. LIBERTAD) | Y17: -12.072125, -75.210097
A18: 8 | B18: 10421732812 | C18: MURGA CERNA LAZARO IVAN | D18: CAJAMARCA | E18: CAJAMARCA | F18: CAJAMARCA | G18: JR. CHEPEN # 345, BARRIO SAN JOSE, CAJAMARCA | H18: IMC INVERSIONES - CAJAMARCA | I18: 076-357959 / 938222416 / 986349476 | J18: MURGA CERNA IVAN | K18: Imc_inversiones@hotmail.com | M18: ELECTRICO+COMBUSTION | N18: DIST+STAM | O18: VIGENTE | P18: FY111 | S18: SI | T18: BCP | U18: 245-71522247-0-19 | V18: 00224517152224701999 | X18: (REF. CERCA AL JARDIN SARA MACDOUGALL) | Y18: -7.1515519,-78.5212845
A19: 9 | B19: 20612160580 | C19: GRUPO FENOR HERRAMIENTAS Y REPUESTOS S.A.C. | D19: AYACUCHO | E19: HUAMANGA | F19: AYACUCHO | G19: AV. RAMON CASTILLA 531, AYACUCHO | H19: MULTISERVICIOS SR DE CANICRUZ | I19: 938458835 / 954850061 | J19: FRITZ EULOGIO BONIFACIO | K19: estrellacasle@gmail.com | M19: ELECTRICO | N19: STAM | O19: VIGENTE | P19: FY111 | S19: SI | T19: BCP | U19: 22094474225010 | V19: 00222019447422501021 | X19: (REF. A MEDIA CDRA ANTES DE LLEGAR AL PTE EJERCITO) | Y19: -13.164261, -74.217998
A20: 10 | B20: 10426366911 | C20: LOZANO HUAMAN EVA LUZ | D20: AYACUCHO | E20: HUAMANGA | F20: AYACUCHO | G20: JR. PROTZEL 291 | H20: MAQUIMARCEL | I20: 066 633948 / 066 621022 / 966110536 | J20: EVA LOZANO | K20: evalozanoh@hotmail.com | M20: ELECTRICO+COMBUSTION | N20: DIST+STAM | O20: VIGENTE | P20: FY111 | X20: (REF. A MEDIA CDRA DEL MERCADO MAGDALENA) | Y20: -13.1586731,-74.2196126
A21: 11 | B21: 20101190227 | C21: ELECTRO COMERCIAL INTI S.R.L. | D21: LIMA | E21: LIMA | F21: CERCADO DE LIMA | G21: JR. WASHINGTON 1509, CERCADO DE LIMA | H21: ELECTRO COMERCIAL INTI S.R.L. | I21: 4243100 / 4331306 / 989987254 / 993 395 065 | J21: SRTA CLAUDIA O MARIELA | K21: elcointi2@hotmail.com | M21: ELECTRICO+COMBUSTION | N21: STAM | O21: VIGENTE | P21: FY111 | S21: SI | T21: BCP | U21: 191-2492881-0-14 | V21: 00219100249288101452 | X21: (FALTA INFO) | Y21: -12.060441008898772, -77.03901852561218
A22: 12 | B22: 20227395576 | C22: EMPRESA DE INTERES LOCAL HIDROELECTRICA S.A. DE CHACAS | D22: ANCASH | E22: ASUNCION | F22: CHACAS | G22: JR. LIMA S/N, CHACAS | H22: EILHICHA S.A. | I22: 043 837101 / 943139036 | J22: LINO PRUNERI | K22: serviciotecnico@eilhicha.com | M22: ELECTRICO+COMBUSTION | N22: DIST+STAM | O22: VIGENTE | P22: FY111 | S22: SI | T22: BCP | U22: 1931898453091 | X22: (FALTA INFO) | Y22: -9.163182, -77.365621
A23: 13 | B23: 20445625371 | C23: MAQUICENTRO REMI S.R.L. | D23: ANCASH | E23: SANTA | F23: CHIMBOTE | G23: AV. JOSE GALVEZ 278, CHIMBOTE | H23: MAQUICENTRO REMI S.R.L. | I23: 994196092 / 946520952 | J23: KENNY MANUEL PAREDES CASTILLO | K23: maq.remi@hotmail.com | M23: ELECTRICO | N23: STAM | O23: VIGENTE | P23: FY111 | X23: (FALTA INFO) | Y23: -9.076835675281705, -78.59021834132994
A24: 14 | B24: 20449280513 | C24: INVERSIONES JODIMAC S.R.L. | D24: MOQUEGUA | E24: MARISCAL NIETO | F24: MOQUEGUA | G24: PROLONGACION ANCASH LT. 12 URB. EL GRAMADAL, MOQUEGUA | H24: INVERSIONES JODIMAC S.R.L. | I24: 053-635098 / 976943344 / 953636742 | J24: JORGE ANDIA | K24: jodimacperu@hotmail.com | M24: ELECTRICO+COMBUSTION | N24: STAM | O24: VIGENTE | P24: FY111 | S24: SI | T24: BCP | U24: 430-1983103-0-76 | V24: 002-430001983103076-72 | X24: (REF. FRENTE AL CASINO EL NARANJAL A UNA CUADRA DE LA UNIVERSIDAD NACIONAL DE MOQUEGUA; CERCA DE PLAZA VEA) | Y24: -17.189186, -70.937618
A25: 15 | B25: 20453974163 | C25: MECHANICAL WORLD SUR S.A.C. | D25: AREQUIPA | E25: AREQUIPA | F25: AREQUIPA | G25: MZ. B LT. 43 URB. ALVAREZ THOMAS, AREQUIPA | H25: MEWOSUR S.A.C | I25: 054-226093 / 958961590 | J25: HILMAR MAMANI / MARIA VILCA | K25: serviciotecnicoaqp@mechanical.pe | M25: ELECTRICO+COMBUSTION | N25: DIST+STAM | O25: VIGENTE | P25: FY111 | S25: SI | T25: BCP | U25: 215-2045870-0-69 | V25: 002-215-002045870069-25 | X25: (REF. POR EL CRUCE DE AV. VENEZUELA, CON AV. DOLORES) | Y25: -16.409121, -71.527843
A26: 16 | B26: 20474318169 | C26: FAST SERVICE AyM S.R.L. | D26: LIMA | E26: LIMA | F26: SAN BORJA | G26: AV. ANGAMOS ESTE 2425 URB TORRES DE LIMATAMBO, SAN BORJA | H26: FASAM S.R.L. | I26: 01-2251388 / 998366678 / 994152404 | J26: MARIANO MALAGA | K26: Mmalaga@fastserviceaym.com | M26: ELECTRICO+COMBUSTION | N26: STAM | O26: VIGENTE | P26: FY111 | S26: SI | T26: BCP | U26: 191-2171877-0-49 | V26: 00219100217187704954 | X26: (FALTA INFO) | Y26: -12.111762, -77.005662
A27: 17 | B27: 20608299735 | C27: MAQUIMAX.PE E.I.R.L. | D27: LA LIBERTAD | E27: TRUJILLO | F27: TRUJILLO | G27: AV. CESAR VALLEJO 1084 ARANJUEZ, TRUJILLO | H27: MAQUIMAX | I27: 044-427402 / 949642315 / 945010707 | J27: WILDER REYES | K27: Serviciotecnico@quimicaperuana.pe | M27: ELECTRICO+COMBUSTION | N27: DIST+STAM | O27: VIGENTE | P27: FY111 | S27: SI | T27: BCP | U27: 570-9916412-0-51 | V27: 002-570-009916412051-03 | X27: (FALTA INFO) | Y27: -8.104265, -79.012518
A28: 18 | B28: 20487194655 | C28: MOIRA NEGOCIOS Y SERVICIOS S.R.L. | D28: JUNIN | E28: SATIPO | F28: SATIPO | G28: JR. JUNIN NRO. 231 URB. SATIPO, SATIPO | H28: MOIRA N&S S.R.L. | I28: 064 545074 / 995783787 / 964731999 | J28: CEDRIC ALCANTARA | K28: cedric.lanyi@gmail.com | M28: ELECTRICO+COMBUSTION | N28: STAM | O28: EVALUACION | P28: FY111 | S28: SI | T28: BCP | U28: 5251834508-0-12 | X28: (FALTA INFO) | Y28: -11.2504425,-74.6371091
A29: 19 | B29: 20487858243 | C29: R & C SOLUCIONES ELECTRICAS S.R.L. | D29: CAJAMARCA | E29: JAEN | F29: JAEN | G29: PJE. LAS CIDRAS 124 JAEN CENTRO, JAEN | H29: R & C SOLUCIONES ELECTRICAS S.R.L. | I29: 976646029 | J29: YONIL RUIZ | K29: ryc_solucioneselectricas@outlook.com | M29: ELECTRICO+COMBUSTION | N29: STAM | O29: VIGENTE | P29: FY111 | S29: SI | T29: BCP | U29: 30506598587025 | V29: 00230510659858702514 | X29: (REF. MITAD DE LA CDRA 2 DE ORELLANA) | Y29: -5.7100766,-78.8114219
A30: 20 | B30: 20494382815 | C30: KIMBERLY MOTORS E.I.R.L. | D30: ICA | E30: NASCA | F30: NASCA | G30: CAL. ARICA 108, 116, NAZCA | H30: KIMBERLY MOTORS | I30: 056-324601 / 956946643 | J30: MERY | K30: kimberlymotors@outlook.es | M30: ELECTRICO | N30: DIST+STAM | O30: VIGENTE | P30: FY111 | X30: (REF. DONDE ESTA LA TIENDA DE MARCA HONDA DEL PERU, ANTES DEL PUENTE VIEJO, A UNA CDRA. DE PLAZA DE ARMAS) | Y30: -14.829344, -74.937215
A31: 21 | B31: 20495627722 | C31: DISTRIBUIDORA FERRETERA LA UNION S.R.L | D31: CAJAMARCA | E31: CAJAMARCA | F31: CAJAMARCA | G31: JR. DEL BATAN 466, CAJAMARCA | H31: DF UNION S.R.L. | I31: 076-776199 / 976957727 / 976668884 | J31: JOSÉ WINTER SANGAY CHICLOTE | K31: servtecdflaunion@gmail.com | M31: ELECTRICO | N31: DIST+STAM | O31: VIGENTE | P31: FY111 | S31: SI | T31: BCP | U31: 245-1468107-0-09 | V31: 002-245-001468107009-91 | X31: (REF. 5 DRAS ANTES DE LA PLAZA DE ARMAS) | Y31: -7.153924443700108, -78.51542560985915
A32: 22 | B32: 20506437513 | C32: EXPLORA PERU E.I.R.L. | D32: APURIMAC | E32: AYMARAES | F32: CHALHUANCA | G32: JR. LIMA S/N ESQUINA CON PANAMERICANA, CHALHUANCA | H32: EXPLORA PERU E.I.R.L. | I32: 998894886 / 995386213 | J32: JOSE REYES | K32: exploraperu.pe@gmail.com | M32: ELECTRICO+COMBUSTION | N32: STAM MINERIA | O32: VIGENTE | P32: FY111 | S32: SI | T32: BCP | U32: 1938446627062 | V32: 00219300844662706210 | X32: (FALTA INFO) | Y32: -14.294097514270264, -73.24822120628318
A33: 23 | B33: 20506591431 | C33: MECHANICAL WORLD S.A.C. | D33: LIMA | E33: LIMA | F33: SAN MIGUEL | G33: AV. ELMER FAUCETT 321 MARANGA, SAN MIGUEL | H33: MECHANICAL WORLD S.A.C. | I33: 4525127 / 998124650 / 924094483 | J33: JIM GARCIA | K33: jgarcia@mechanical.pe | M33: ELECTRICO+COMBUSTION | N33: DIST+STAM | O33: VIGENTE | P33: FY111 | X33: (FALTA INFO) | Y33: -12.0680264,-77.0977869
A34: 24 | B34: 20512531751 | C34: KVR3 SOCIEDAD ANONIMA CERRADA - KVR3 S.A.C. | D34: LIMA | E34: LIMA | F34: EL AGUSTINO | G34: AV. NICOLAS AYLLON 2355, EL AGUSTINO | H34: KVR3 SAC | I34: 3263600 / 3472356 / 970363690 | J34: CLAUDIA VARGAS | K34: Atencionalcliente@kvr3.pe | M34: ELECTRICO | N34: DIST+STAM | O34: VIGENTE | P34: FY111 | X34: (FALTA INFO) | Y34: -12.0615139,-76.9801814
A35: 25 | B35: 20518795466 | C35: CONSTRUDECOR PERU S.A.C. | D35: LIMA | E35: LIMA | F35: INDEPENDENCIA | G35: CALLE LOS TORNOS 182 | H35: CONSTRUDECOR PERU S.A.C. | I35: 994291572 / 982007592 | J35: KAREN VILLANUEVA | K35: SERVICIOTECNICOCONSTRUDECORPERU@GMAIL.COM | M35: ELECTRICO | N35: STAM | O35: VIGENTE | P35: FY111 | S35: SI | T35: BCP | U35: 191-2609-162-0-71 | V35: 00219100260916207151 | X35: (FALTA INFO) | Y35: -11.9791391,-77.0610876
A36: 26 | B36: 20519224683 | C36: MUNDO CONSTRUCTOR S.A.C. | D36: LIMA | E36: LIMA | F36: VILLA EL SALVADOR | G36: CAL. EBANISTA MZ. I1 LT. 1 PARCELA 2, PARQUE INDUSTRIAL, VILLA EL SALVADOR | H36: MUNDO CONSTRUCTOR S.A.C | I36: 2873438 / 936962833 / 994005644 | J36: VANESSA RODARTE | K36: servicios@mundoconstructor.com.pe | M36: ELECTRICO+COMBUSTION | N36: DIST+STAM | O36: VIGENTE | P36: FY111 | S36: SI | T36: BCP | U36: 1931734585059 | V36: 00219300173458505912 | X36: (FALTA INFO) | Y36: -12.201325, -76.932686
A37: 27 | B37: 20521289270 | C37: ERANMIAL S.R.L | D37: LIMA | E37: LIMA | F37: S. J. DE LURIGANCHO | G37: AV. CANTO REY 502, SAN JUAN DE LURIGANCHO | H37: ERANMIAL S.R.L | I37: 951555407 / 978778621 | J37: ERNESTO VELASQUEZ | K37: operaciones@eranmial.com.pe | M37: ELECTRICO | N37: STAM | O37: EVALUACION | P37: FY111 | S37: SI | T37: BCP | U37: 1931790135070 | V37: 00219300179013507016 | X37: (FALTA INFO) | Y37: -11.977211, -76.998739
A38: 28 | B38: 20521881217 | C38: TOOLS HOME & SERVICE S.A.C. | D38: LIMA | E38: LIMA | F38: SAN LUIS | G38: JR. FRANCISCO VIDAL DE LAOS 435, SAN LUIS | H38: TOOLS HOME | I38: 323-3333 / 998272507 | J38: CARLOS GUTIERRES | K38: servicio.toolshome@gmail.com; servicio@toolshome.pe | L38: servicio@toolshome.pe | M38: ELECTRICO+COMBUSTION | N38: STAM | O38: VIGENTE | P38: FY111 | S38: SI | T38: BCP | U38: 191-1832792-0-49 | V38: 002-191-001832792049-54 | X38: (FALTA INFO) | Y38: -12.072173,-76.998761
A39: 29 | B39: 20523348451 | C39: INVERSIONES LA BANCHERO S.A.C. | D39: LIMA | E39: LIMA | F39: SAN JUAN DE LURIGANCHO | G39: MZ. F, LT. 15 LOS ALAMOS, SAN JUAN DE LURIGANCHO | H39: INVERSIONES LA BANCHERO SAC | I39: 01-3873647 / 989815391 / 984285423 / 970766061 | J39: JOSE MONAGO | K39: inversioneslabanchero@hotmail.com | M39: ELECTRICO | N39: STAM | O39: VIGENTE | P39: FY111 | S39: SI | T39: BCP | U39: 1912163687022 | V39: 00219100216368702258 | X39: (REF. FRENTE A LA ESTACION SANTA ROSA) | Y39: -11.968254, -76.993924
A40: 30 | B40: 20523555759 | C40: GMR INVERSIONES S.A.C. | D40: LIMA | E40: LIMA | F40: SAN JUAN DE LURIGANCHO | G40: MZ A LT 9 URB BUENOS AIRES- SAN JUAN DE LURIGANCHO | H40: GMR INVERSIONES S.A.C. | I40: 01-7044140 / 936080318 / 953100137 | J40: YOSELIN HERNANDEZ | K40: servicio.tecnico@gmrinversiones.com.pe | M40: ELECTRICO | N40: DIST+STAM | O40: VIGENTE | P40: FY111 | S40: SI | T40: BCP | U40: 191-1913039-0-25 | X40: (FALTA INFO) | Y40: -11.991847, -77.014880
A41: 31 | B41: 20525979602 | C41: MECHANICAL WORLD PIURA S.A.C. | D41: PIURA | E41: PIURA | F41: PIURA | G41: LAS CAMELIAS MZ. W LOTE 30 URB. MIRAFLORES I ETAPA PIURA. | H41: MECHANICAL STORE | I41: 073-322818 / 978721961 | J41: JORGE CHUQUIPOMA | K41: hector.rodriguez@mechanicalpiura.pe | M41: ELECTRICO+COMBUSTION | N41: DIST+STAM | O41: VIGENTE | P41: FY111 | S41: SI | T41: BCP | U41: 475-1808600-0-65 | V41: 002-475-001808600065-22 | X41: (FALTA INFO) | Y41: -5.192102, -80.618621
A42: 32 | B42: 20527979189 | C42: SERVICIO TECNICO DENIS EIRL | D42: CUSCO | E42: CUZCO | F42: WANCHAQ | G42: AV. LA PAZ 749, WANCHAQ | H42: SERVICIO TECNICO DENIS E.I.R.L. | I42: 084-251684 / 985000853 | J42: DENIS MAITA / DIONISIO MAITA | K42: serviciotecdenis@hotmail.com | M42: ELECTRICO+COMBUSTION | N42: STAM | O42: VIGENTE | P42: FY111 | S42: SI | T42: BCP | U42: 285-1623192-0-65 | X42: (FALTA INFO) | Y42: -13.530422, -71.967766
A43: 33 | B43: 20534883588 | C43: E.BARRETO SOLUCIONES S.A.C. | D43: ICA | E43: NASCA | F43: NASCA | G43: CAL. JUAN MATTA 202, NASCA | H43: E. BARRETO SOLUCIONES S.A.C. | I43: 056 523413 / 968121311 | J43: ELIZABETH BARRETO | K43: ebarreto-soluciones1@hotmail.com | M43: ELECTRICO | N43: STAM | O43: VIGENTE | P43: FY111 | X43: (REF. A ESPLADAS DE LA AGENCIA FLORES) | Y43: -14.827302, -74.945228
A44: 34 | B44: 10409524732 | C44: José Alberto Mendoza Rojas | D44: ICA | E44: CHINCHA | F44: CHINCHA ALTA | G44: CC NUEVO TACORA STAND 152/FRENTE AL COLEGIO ABRAHAM LINCOLN | H44: José Alberto Mendoza Rojas | I44: 973904277 | J44: JOSÉ ALBERTO MENDOZA ROJAS | K44: sertecchinchay@gmail.com | M44: ELECTRICO+COMBUSTION | N44: STAM | O44: VIGENTE | P44: FY111 | S44: SI | T44: BCP | U44: 3154679516054 | V44: 00231500467951605401 | X44: (FALTA INFO) | Y44: -13.421806,-76.133427
A45: 35 | B45: 20535848450 | C45: NIRVANA COMPANY SERVICE S.A.C. | D45: LIMA | E45: LIMA | F45: SAN JUAN DE MIRAFLORES | G45: AV. DE LOS HEROES NRO. 900 URB. SAN JUAN ZN. D / SAN JUAN DE MIRAFLORES | H45: MAKITA STORE PERÚ BY NIRVANA COMPANY SERVICE S.A.C. | I45: 975013100 | J45: OMAR FIESTAS B. / LUZ VERA | K45: ventas@nirvana-company.com | M45: ELECTRICO+COMBUSTION | N45: DIST+STAM | O45: VIGENTE | P45: FY111 | S45: SI | T45: BCP | U45: 194-2106374-0-04 | V45: 002-194-002106374004-93 | X45: (FALTA INFO) | Y45: -12.2013007,-76.9308844
A46: 36 | B46: 20535848450 | C46: NIRVANA COMPANY SERVICE S.A.C. | D46: LIMA | E46: LIMA | F46: VILLA EL SALVADOR | G46: AV. DE LOS HEROES NRO. 900 URB. SAN JUAN ZN. D / SAN JUAN DE MIRAFLORES | H46: MAKITA STORE PERÚ BY NIRVANA COMPANY SERVICE S.A.C. | I46: 975013100 | J46: OMAR FIESTAS B. / LUZ VERA | K46: ventas@nirvana-company.com | M46: ELECTRICO+COMBUSTION | N46: DIST+STAM | O46: VIGENTE | P46: FY111 | S46: SI | T46: BCP | U46: 194-2106374-0-04 | V46: 002-194-002106374004-93 | X46: (FALTA INFO) | Y46: -12.2013007,-76.9308844
A47: 37 | B47: 20536973215 | C47: GRUPO CAHEMA S.A.C. | D47: LIMA | E47: LIMA | F47: SURQUILLO | G47: AV. ANGAMOS ESTE 2130, SURQUILLO | H47: GRUPO CAHEMA S.A.C. | I47: 01 2609802 / 998325498 / 981356839 | J47: MARLEE CHOQUECAHUANA | K47: grupocahemasac@hotmail.com | M47: ELECTRICO+COMBUSTION | N47: DIST+STAM | O47: VIGENTE | P47: FY111 | S47: SI | T47: BCP | U47: 193-1848767-0-12 | V47: 002-193-001848767012-19 | X47: (FALTA INFO) | Y47: -12.112336, -77.007493
A48: 38 | B48: 20537472562 | C48: MECHANICAL WORLD CONO SUR S.A.C | D48: LIMA | E48: LIMA | F48: SURCO | G48: JR. VIÑA LARIENA MZ. A31, LT. 8, SANTIAGO DE SURCO | H48: MECHANICAL WORLD CONO SUR S.A.C. | I48: 3960303 / 946456498 | J48: ESTEFANIA ZUBIATE | K48: atencionlimasur@mechanical.pe | M48: ELECTRICO | N48: DIST+STAM | O48: VIGENTE | P48: FY111 | S48: SI | T48: BCP | U48: 194-2179262-0-46 | V48: 0011-0921-0200243541 | X48: (FALTA INFO) | Y48: -12.173269, -76.996918
A49: 39 | B49: 20540087751 | C49: MAKSERVICES TRUJILLO S.A.C | D49: LA LIBERTAD | E49: TRUJILLO | F49: TRUJILLO | G49: AV. AMERICA SUR 1160, URB PALERMO, TRUJILLO | H49: MAKSERVICES TRUJILLO | I49: 951771103 | J49: UBELSER MENDOZA / DAVID MENDOZA | K49: st-trujillo@makservicesperu.com | M49: ELECTRICO+COMBUSTION | N49: DIST+STAM | O49: VIGENTE | P49: FY111 | S49: S | T49: BCP | U49: 570-208154-30-60 | V49: 00257000208154306006 | X49: (FALTA INFO) | Y49: -8.111104, -79.013553
A50: 40 | B50: 20540087751 | C50: MAKSERVICES TRUJILLO S.A.C | D50: LA LIBERTAD | E50: TRUJILLO | F50: TRUJILLO | G50: AV. AMERICA SUR 1160, URB PALERMO, TRUJILLO | H50: MAKSERVICES TRUJILLO | I50: 951771103 | J50: UBELSER MENDOZA / DAVID MENDOZA | K50: st-trujillo@makservicesperu.com | M50: ELECTRICO+COMBUSTION | N50: DIST+STAM MINERIA | O50: EVALUACION | P50: FY111 | S50: SI | T50: BCP | U50: 570-208154-30-60 | V50: 00257000208154306006 | X50: (FALTA INFO) | Y50: -8.111104, -79.013553
A51: 41 | B51: 20546163769 | C51: GRUPO KALU S.A.C. | D51: APURIMAC | E51: COTABAMBAS | F51: COYLLURQUI (PAMPUTA) | G51: COMUNIDAD CAMPESINA S/N, COYLLURQUI | H51: GRUPO KALU S.A.C. | I51: 944257963 | J51: LUIS VILCHEZ | K51: grupo.kalu@hotmail.com | M51: ELECTRICO | N51: STAM MINERIA | O51: VIGENTE | P51: FY111 | S51: SI | T51: CONTINENTAL | U51: 0011-0361-30-0200391822 | X51: (REF. FRENTE A LA PLAZA DE PAMPUTA) | Y51: -13.971135, -72.396409
A52: 42 | B52: 20546163769 | C52: GRUPO KALU S.A.C. | D52: APURIMAC | E52: COTABAMBAS | F52: COYLLURQUI (PAMPUTA) | G52: COMUNIDAD CAMPESINA S/N, COYLLURQUI | H52: GRUPO KALU S.A.C. | I52: 944257963 | J52: LUIS VILCHEZ | K52: grupo.kalu@hotmail.com | M52: ELECTRICO+COMBUSTION | N52: STAM MINERIA | O52: VIGENTE | P52: FY111 | S52: SI | T52: CONTINENTAL | U52: 0011-0361-30-0200391822 | X52: (REF. FRENTE A LA PLAZA DE PAMPUTA) | Y52: -13.971135, -72.396409
A53: 43 | B53: 20546382649 | C53: MUNDO MAQUINA ORE E.I.R.L. | D53: LIMA | E53: BARRANCA | F53: BARRANCA | G53: JR. JOSE OLAYA 266, BARRANCA | H53: MUNDO MAQUINA ORE | I53: 953693346 / 987202902 | J53: RONALD ORE ESCALANTE | K53: r.ore@mundomaquina.com.pe | M53: ELECTRICO+COMBUSTION | N53: DIST+STAM | O53: VIGENTE | P53: FY111 | S53: SI | T53: BCP | U53: 235-1973574-0-26 | V53: 00223500197357402608 | X53: (FALTA INFO) | Y53: -10.749954, -77.759727
A54: 44 | B54: 20561407518 | C54: TECNICAS PERUANAS S.A.C. | D54: LAMBAYEQUE | E54: CHICLAYO | F54: JOSE LEONARDO ORTIZ | G54: CAL. TAHUANTINSUYO 1007, URB. SAN LORENZO, JOSE LEONARDO ORTIZ | H54: TECNICAS PERUANAS | I54: 986384777 / 992869440 | J54: NORMA CASTAÑEDA | K54: tecnikaspe@gmail.com | M54: ELECTRICO | N54: STAM | O54: VIGENTE | P54: FY111 | S54: SI | T54: BCP | U54: 4408738516080 | V54: 00244000873851608066 | X54: (REF. A UNA CDRA. DEL TEMPLO DE LOS MORMONES) | Y54: -6.760580707765693, -79.8420775585291
A55: 45 | B55: 20564412989 | C55: PUMA CENTER S.C.R.L. | D55: CUSCO | E55: CANCHIS | F55: SICUANI | G55: MALECON TECHO OBRERO N° 70, SICUANI | H55: PUMA HOME CENTER | I55: 084-351545 | J55: ERACLIO ORUE | K55: serviciotecnico@pumahomecenter.com | M55: ELECTRICO+COMBUSTION | N55: DIST+STAM | O55: VIGENTE | P55: FY111 | X55: (FALTA INFO) | Y55: -14.280632, -71.227920
A56: 46 | B56: 20600099257 | C56: SERVICIOS ZETA GAMUS E.I.R.L. | D56: PIURA | E56: PIURA | F56: VEINTISEIS DE OCTUBRE | G56: AV. CIRCUNVALACION MZ. I4 LT. 21, VEINTISEIS DE OCTUBRE | H56: FAST MOTORS | I56: 953263203 | J56: JOAN GAONA | K56: fastmotors_central@outlook.com | M56: ELECTRICO+COMBUSTION | N56: STAM | O56: VIGENTE | P56: FY111 | X56: (FALTA INFO) | Y56: -5.188612, -80.667536
A57: 47 | B57: 20600407148 | C57: MAQUICASA E.I.R.L. | D57: LIMA | E57: LIMA | F57: LIMA | G57: JR. WASHINGTON NRO. 1698 | H57: MAQUICASA E.I.R.L. | I57: 4312039 / 998889720 | J57: ARTURO CASTAÑEDA ALEGRIA | K57: ventas@maquicasaperu.com | M57: ELECTRICO+COMBUSTION | N57: DIST+STAM | O57: VIGENTE | P57: FY111 | X57: (REF. CERCA AL POLICLINICO CHINCA SEGURO SOCIAL) | Y57: -12.062016, -77.039005
A58: 48 | B58: 20600774345 | C58: CONGLOMERADO INNOVATEC PERU E.I.R.L. | D58: PUNO | E58: SAN ROMAN | F58: JULIACA | G58: JR LA REVOLUCION 193, JULIACA | H58: CONGLOMERADO INNOVATEC PERU E.I.R.L (Innovatec maquinarias) | I58: 977410743 / 988999948 | J58: JHON CASTILLO | K58: Innovatekp@hotmail.com | M58: ELECTRICO+COMBUSTION | N58: DIST+STAM | O58: VIGENTE | P58: FY111 | S58: SI | T58: BCP | U58: 405-2321542-0-27 | V58: 00240500232154202796 | X58: (FALTA INFO) | Y58: -15.4895397,-70.1331473
A59: 49 | B59: 20601045045 | C59: CONSORCIO AACV S.A.C. | D59: LIMA | E59: LIMA | F59: CHORRILLOS | G59: AV. GUARDIA CIVIL 631, CHORRILLOS | H59: CONSORCIO AACV S.A.C. | I59: 3895794 / 981585814 | J59: JHON CAÑAHUA | K59: servicio.makita@consorcioaacv.com | M59: ELECTRICO+COMBUSTION | N59: DIST+STAM | O59: VIGENTE | P59: FY111 | S59: SI | T59: BCP | U59: 194-2464712-0-79 | V59: 002-194-002464712079-99 | X59: (FALTA INFO) | Y59: -12.17962,-76.99778
A60: 50 | B60: 20601045045 | C60: CONSORCIO AACV S.A.C. | D60: LIMA | E60: LIMA | F60: CHORRILLOS | G60: AV. GUARDIA CIVIL 631, CHORRILLOS | H60: CONSORCIO AACV S.A.C. | I60: 3895794 / 981585814 | J60: JHON CAÑAHUA | K60: servicio.makita@consorcioaacv.com | M60: ELECTRICO+COMBUSTION | N60: DIST+STAM | O60: VIGENTE | P60: FY111 | S60: SI | T60: BCP | U60: 194-2464712-0-79 | V60: 002-194-002464712079-99 | X60: (FALTA INFO) | Y60: -12.17962,-76.99778
A61: 51 | B61: 20601350417 | C61: TAYM INVERSIONES & ASESORIA INTEGRAL S.A.C. | D61: LIMA | E61: LIMA | F61: SAN MIGUEL | G61: CAL. MANUEL FERREYROS S/N, MZ. C, LT. 17, SAN MIGUEL | H61: TAYM S.A.C. | I61: 502-8140 / 942478318 | J61: ALAN YZAZIGA | K61: serviciotecnico@taymsac.pe | M61: ELECTRICO+COMBUSTION | N61: DIST+STAM | O61: VIGENTE | P61: FY111 | S61: SI | T61: BCP | U61: 19399532167040 | V61: 002193199532167040018 | X61: (FALTA INFO) | Y61: -12.069345, -77.103041
A62: 52 | B62: 20601646588 | C62: COMERCIOS MAQUIHER E.I.R.L. | D62: ICA | E62: PISCO | F62: PISCO | G62: CAL. COMERCIO 450, PISCO | H62: COMERCIOS MAQUIHER E.I.R.L. | I62: 51 981 027 976 | J62: EUGENIO QUISPE | K62: maquiher@hotmail.com | M62: ELECTRICO | N62: STAM | O62: EVALUACION | P62: FY111 | X62: (FALTA INFO) | Y62: -13.713341, -76.203858
A63: 53 | B63: 20602222749 | C63: QUICK TOOLS E.I.R.L. | D63: LIMA | E63: LIMA | F63: SAN MARTIN DE PORRES | G63: MZ. D, LT 102, ASOC. SAN JUAN DE DIOS 1 ETAPA | H63: QUICK TOOLS E.I.R.L. | I63: 993263550 / 957917803 | J63: FREDY CARRASCAL / LUIS LARCO | K63: quick.toolsmakita@gmail.com | M63: ELECTRICO+COMBUSTION | N63: STAM | O63: VIGENTE | P63: FY111 | S63: SI | T63: BCP | U63: 191-38248563-0-10 | V63: 00219113824856301058 | X63: CDRA 36; ENTRE IZAGUIRRE Y ANTUNES DE MAYOLO | Y63: -11.993674, -77.083814
A64: 54 | B64: 20602326765 | C64: INVERSIONES HAMMERCOM S.C.R.L. | D64: HUANUCO | E64: HUANUCO | F64: AMARILIS | G64: AV. MARCOS DURAN MARTEL 205 | H64: INVERSIONES HAMMERCOM S.C.R.L. | I64: 927391320 / 967803731 | J64: DANIEL POZO / WILSON CAYCO | K64: FEYCOMTEC@HOTMAIL.COM | M64: ELECTRICO | N64: STAM | O64: VIGENTE | P64: FY111 | S64: SI | T64: BCP | U64: 3652638270059 | V64: 00236500263827005954 | X64: (FALTA INFO) | Y64: -9.934877, -76.236538
A65: 55 | B65: 20602909396 | C65: MAKISERTEC E.I.R.L. | D65: AYACUCHO | E65: SANCOS | F65: LUCANAS | G65: AV. MICAELA BASTIDA MZ "D" LT "21" CENTRO POBLADO SANTA FILOMENA, LUCANAS | H65: MULTI SERVICIOS SHADDAI | I65: 942322837 / 987333320 | J65: ANTONIO INCA | K65: makisertec@gmail.com | M65: ELECTRICO | N65: STAM MINERIA | O65: VIGENTE | P65: FY111 | S65: SI | T65: BCP | U65: 1919901766036 | V65: 00219100990176603658 | X65: (FALTA INFO) | Y65: -15.360593, -74.274965
A66: 56 | B66: 20603189834 | C66: GLOBAL SERVICORP E.I.R.L. | D66: LIMA | E66: LIMA | F66: CERCADO DE LIMA | G66: AV. ARGENTINA 308, INT. 276 CC. LA BELLOTA II, CERCADO DE LIMA | H66: GLOBALSERVICORP E.I.R.L. | I66: 01-7825024 / 941706400 | J66: OSCAR RIOS | K66: globalservicorp.peru@gmail.com | M66: ELECTRICO+COMBUSTION | N66: STAM | O66: VIGENTE | P66: FY111 | S66: SI | T66: INTERBANK | U66: 2003005335696 | V66: 00320000300533569637 | X66: (FALTA INFO) | Y66: -12.042723, -77.045676
A67: 57 | B67: 20604254958 | C67: MEGA TOOLS SERVICE E.I.R.L. | D67: LIMA | E67: HUAURA | F67: HUACHO | G67: JR ATAHUALPA 229 | H67: MEGA TOOLS SERVICE E.I.R.L. | I67: 959346000 | J67: JERSSON | K67: service@megatools.com.pe | M67: ELECTRICO | N67: STAM | O67: VIGENTE | P67: FY111 | S67: SI | T67: BCP | U67: 3352557959005 | V67: 00233500255795900587 | X67: (AL COSTADO DE CAJA PRYMERA) | Y67: -11.1073916, -77.6046113
A68: 58 | B68: 20605338110 | C68: EL GRAN SHADDAI E.I.R.L. | D68: AREQUIPA | E68: CARAVELI | F68: CHALA | G68: AAHH. PRADO AV. EMANCIPACION MZ. 51, LT. 2F, CHALA | H68: EL GRAN SHADDAI | I68: 942322837 / 987333320 | J68: ANTONIO INCA | K68: elgranshadday@gmail.com | M68: ELECTRICO | N68: DIST+STAM | O68: VIGENTE | P68: FY111 | S68: SI | T68: BCP | U68: 1918745239045 | V68: 00219100874523904550 | X68: (FALTA INFO) | Y68: -15.850111, -74.254604
A69: 59 | B69: 20606393505 | C69: FLOWERS GROUP SERVICE SRL | D69: LORETO | E69: MAYNAS | F69: IQUITOS (NUEVO: BELEN) | G69: AV GARCIA SAENZ 254 | H69: FLOWERS GROUP SERVICE S.R.L. | I69: 918615261 / 900834560 | J69: MOISÉS FLORES | K69: services_ag2011@hotmail.com | M69: ELECTRICO | N69: STAM | O69: VIGENTE | P69: FY111 | X69: (FALTA INFO) | Y69: -3.7597643,-73.2514892
A70: 60 | B70: 20606974401 | C70: LA BIELA ROTA SAC | D70: JUNIN | E70: HUANCAYO | F70: EL TAMBO | G70: AV. MARISCAL CASTILLA N 1378 | H70: LA BIELA ROTA (HUANCAYO) | I70: 948519082 | J70: RAUL | K70: la_biela_rota@outlook.com | M70: ELECTRICO+COMBUSTION | N70: STAM | O70: EVALUACION | P70: FY111 | S70: SI | T70: INTERBANK | U70: 5003004808118 | X70: (FALTA INFO) | Y70: -12.055854, -75.219908
A71: 61 | B71: 20454012195 | C71: INTERMAC SRL | D71: AREQUIPA | E71: AREQUIPA | F71: AREQUIPA | G71: AV. PARRA 99B | H71: INTERMAC | I71: 959924870 / 932272090 / 054 220930 | J71: ALVARO DELGADO / JORGE VALDERRAMA | K71: negociosintermac@gmail.com | M71: ELECTRICO | N71: DIST+STAM | O71: VIGENTE | P71: FY111 | S71: SI | T71: BCP | U71: 215-1500333-0-95 | V71: 002-215-001500333095-26 | X71: (REF. A MEDIA CDRA MAS ABAJO DEL INSTITUTO DEL SUR / FRENTE AL CASINO MILITAR) | Y71: -16.406232028982803, -71.54058141881117
A72: 62 | B72: 20607464091 | C72: TOOLSTORE SEMIN S.A.C. | D72: AREQUIPA | E72: AREQUIPA | F72: JOSE LUIS BUSTAMANTE Y RIVERO | G72: CALLE COLON 142-C | H72: TOOLSTORE SEMIN S.A.C. | I72: 975659316 | J72: VICTOR LAZO | K72: toolstoresemin@gmail.com | M72: ELECTRICO | N72: DIST+STAM | O72: VIGENTE | P72: FY111 | S72: SI | T72: INTERBANK | U72: 300-3003143231 | V72: 003-300-003003143231-10 | X72: (REF. ANTES DE LLEGAR AL COLEGIO INNOVA SCHOOL) | Y72: -16.43759578057298, -71.50727332040103
A73: 63 | B73: 20529114355 | C73: MULTISERVICIOS WINNERS EIRL | D73: PASCO | E73: PASCO | F73: SIMON BOLIVAR | G73: JR. 28 DE JULIO 100 (CENTRO POBLADO DE PARAGIA) | H73: MULTISERVICIOS WINNERS | I73: 948442678 | J73: SR FRANK CERNA ESPINOZA | K73: frank1093@hotmail.com | M73: ELECTRICO+COMBUSTION | N73: STAM | O73: VIGENTE | P73: FY111 | X73: (REF. EN OVALO DE PARAGIA) | Y73: -10.673315894932545, -76.26682718673872
A74: 64 | B74: 20532823774 | C74: GT GLOBAL TOOLS S.R.L. | D74: TACNA | E74: TACNA | F74: TACNA | G74: AV. CUZCO, URB LA VIRREYNA, MZ. A, LT. 4 | H74: GLOBAL TOOLS | I74: 952880010 | J74: RONI MAMANI ORCO | K74: gt.globla.servicio@gmail.com | M74: ELECTRICO | N74: STAM | O74: VIGENTE | P74: FY111 | S74: SI | T74: BCP | U74: 540-2209573-0-63 | V74: 00254000220957306330 | X74: (REF. A 3 CUADRAS DE PLAZA VEA) | Y74: -18.022653333170194, -70.25238049646897
A75: 65 | B75: 20606071974 | C75: JC & S MAQUINARIAS Y REPARACIONES S.A.C. | D75: LIMA | E75: LIMA | F75: PUENTE PIEDRA | G75: AV. BUENOS AIRES MZ E LT 13 ASO ASOCIACION MICAELA BASTIDAS PTE PIEDRA - OVALO ZAPALLAS | H75: JC&S | I75: 947916545 | J75: FRANYA CONTRERAS | K75: sta_makita@jcysmaquinarias.com | M75: ELECTRICO+COMBUSTION | N75: STAM | O75: VIGENTE | P75: FY111 | S75: SI | T75: BCP | U75: 194-7530062-0-31 | V75: 00219400753006203199 | X75: (REF. Entre paradero escuela de oficiales y paradero establo) | Y75: -11.8931443, -77.0683276
A76: 66 | B76: 20608981552 | C76: TECSER INVERSIONES EIRL. | D76: CUSCO | E76: CUSCO | F76: WANCHAQ | G76: AV. DIAGONAL ANGAMOS 2048, URB. SANTA BEATRIZ, WANCHAQ | H76: TECSER PERU | I76: 973142428/ 914223957 | J76: DIEGO QUISPE | K76: tecser.inversiones@hotmail.com | M76: ELECTRICO+COMBUSTION | N76: STAM | O76: VIGENTE | P76: FY111 | S76: SI | T76: CONTINENTAL | U76: 0011-0083-0100014230 | V76: 011083000100014230-35 | X76: (REF. AL COSTADO DEL CONSECIONARIO DE AUTOS RENOLD) | Y76: -13.526454, -71.953369
A77: 67 | B77: 10457128300 | C77: ÑIQUIN GRAUS JUAN HENRY | D77: CAJAMARCA | E77: CAJABAMBA | F77: CAJABAMBA | G77: JR SAN LORENZO S/N - REFERENCIA PUENTE INGENIEROS FRENTE A CAXAGAS | H77: LA CASA DE LA MAQUINA | I77: 940136228/974211750 | J77: JUAN HENRY ÑIQUIN GRAUS/LUIS RAMONÑIQUIN GRAUS | K77: lacasadelamaquina01@gmail.com | M77: ELECTRICO | N77: STAM MINERIA | O77: VIGENTE | P77: FY111 | S77: SI | T77: INTERBANK | U77: 6003141530610 | V77: 003600013141530610 | X77: (FALTA INFO) | Y77: -7.613228, -78.053626
A78: 68 | B78: 10406543612 | C78: MARCOS MIGUEL GUARDIA YAUYO | D78: LIMA | E78: LIMA | F78: LA MOLINA | G78: AV. LOS CHANCAS MZ. K LT. 41 ASOC. LOS PINOS STA ANITA | H78: DAAT SERVICE | I78: 947991766 | J78: MARCOS GUARDIA / DIEGO GUARDIA | K78: marcosgy1918@gmail.com | M78: ELECTRICO | N78: STAM | O78: VIGENTE | P78: FY111 | S78: SI | T78: BCP | U78: 194-97143036-0-77 | X78: (FALTA INFO) | Y78: -12.035101, -76.957488
A79: 69 | B79: 20495122108 | C79: EQUIPOS Y HERRAMIENTAS SAC | D79: ICA | E79: ICA | F79: ICA | G79: AV. JUAN JOSE ELIAS MZ L- LT 10 (REF CRUCE ELIAS CON CALLE CHICLAYO) | H79: EQUIPOS Y HERRAMIENTAS SAC | I79: 946241033 | J79: DIMAS LLAMOCA RODRIGUEZ | K79: ventas.equipo.ica@hotmail.com | M79: ELECTRICO | N79: DIST+STAM | O79: VIGENTE | P79: FY111 | S79: SI | T79: BCP | U79: 380-1927821-0-21 | V79: 00238000192782102146
A80: 70 | B80: 10295495753 | C80: RICARDO RAUL MONTESINOS CALLA | D80: LIMA | E80: LIMA | F80: SURQUILLO | G80: JR. FRANCISCO MORENO NRO. 501 | H80: RICARDO RAUL MONTESINOS CALLA | I80: 929893395 | J80: RICARDO MONTESINOS | K80: rmontesinos@spedimaq.com ; jcastillo@spedimaq.com | M80: ELECTRICO | N80: DIST+STAM | O80: VIGENTE | P80: FY111 | S80: SI | T80: BCP | U80: 194-77567985-0-97
A81: 71 | B81: 20605905031 | C81: JYN HERMANOS | D81: PASCO | E81: OXAPAMPA | F81: OXAPAMPA | G81: JR. INDEPENDECIA CUADRA 7 ESQUINA CON JR. FREY | H81: JYN HERMANOS | I81: 936067412 | J81: PAUL FLORES TABORI | K81: jynhermanos2@gmail.com | M81: ELECTRICO | N81: STAM | O81: VIGENTE | P81: FY111 | S81: SI | T81: BCP | U81: 445-2659806-0-74 | V81: 00244500265980607452
A82: 72 | B82: 20506437513 | C82: EXPLORA PERU E.I.R.L. | D82: APURIMAC | E82: AYMARAES | F82: CHALHUANCA | G82: JR. LIMA S/N ESQUINA CON PANAMERICANA, CHALHUANCA | H82: EXPLORA PERU E.I.R.L. | I82: 998894886 / 995386213 | J82: JOSE REYES | K82: exploraperu.pe@gmail.com | M82: ELECTRICO | O82: VIGENTE | P82: FY111 | S82: SI | T82: BCP | U82: 1938446627062 | V82: 00219300844662706210
A83: 73 | B83: 20602222749 | C83: QUICK TOOLS E.I.R.L. | D83: LIMA | E83: LIMA | F83: SAN MARTIN DE PORRES | G83: MZ. D, LT 102, ASOC. SAN JUAN DE DIOS 1 ETAPA | H83: QUICK TOOLS E.I.R.L. | I83: 993263550 / 957917803 | J83: FREDY CARRASCAL / LUIS LARCO | K83: quick.toolsmakita@gmail.com | M83: ELECTRICO+COMBUSTION | O83: VIGENTE | P83: FY111 | S83: SI | T83: BCP | U83: 191-38248563-0-10 | V83: 00219113824856301058
A84: 74 | B84: 20610514821 | C84: SERVISOLUCIONES PERU EIRL | D84: LA LIBERTAD | E84: TRUJILLO | F84: TRUJILLO | G84: AV. RICARDO PALMA NRO. 429 INT. 3 URB. PALERMO ET. 3 | H84: SERVISOLUCIONES PERU EIRL | I84: 950425503 / 966058042 | J84: CARLOS TRIGOSO / ROXANA LUJAN | K84: SERVISOLUCIONES.PERU@GMAIL.COM | M84: ELECTRICO+COMBUSTION | O84: VIGENTE
A85: 75 | B85: 20606837969 | C85: CORPORACION & SERVICIOS DAVID SOCIEDAD COMERCIAL DE RESPONSABILIDAD LIMITADA-CORP & SERV DAVID S.R.L | D85: AREQUIPA | E85: CARAVELI | F85: CHALA | G85: AV. EMANCIPACIÓN MZA. 32 LOTE. 14B A.H. MANUEL PRADO | H85: CORPORACION & SERVICIOS DAVID SOCIEDAD COMERCIAL DE RESPONSABILIDAD LIMITADA-CORP & SERV DAVID S.R.L | I85: 960368198 / 989309828 | J85: IRWIN DE LA CRUZ | K85: DAVIDCORPYSERVICIOS@GMAIL.COM | M85: ELECTRICO+COMBUSTION | O85: VIGENTE
A86: 76 | B86: 20610613749 | C86: I TOOL STORE | D86: LIMA | E86: HUAURA | F86: HUACHO | G86: JR. ATAHUALPA NRO. 229 (JR. ATAHUALPA - CRUCE ADAN ACEVEDO | H86: I TOOL STORE | I86: 994364117 | J86: OSWALDO MIGUEL NOEL ROMAN | K86: oswaldo.noel@gmail.com; SERVICE@ITOOLS.PE
A87: 77 | B87: 20541514466 | C87: FIVCO MAQUINAS Y HERRAMIENTAS SAC | D87: JUNIN | E87: HUANCAYO | F87: EL TAMBO | G87: JR RICARDO PALMA 470 | H87: CORPORACION FIVCO | I87: 932430433 | J87: Paul Huaman | K87: Technic.makita@fivco.com.pe
B88: 10455246895 | C88: JEAN MUÑOZ MAYCO MICHEL | D88: LIMA | E88: LIMA | F88: ATE | G88: AV LOS VIRREYES MZ D LOTE 20 URB. FORTALEZA ATE | H88: MJ TOOLS SERVICES | I88: 955795819 | J88: Mayco Jean | K88: mjtoolsservice2@gmail.com
B89: 20515100548 | C89: MAKITA PERU S.A. | D89: LIMA | E89: LIMA | F89: LURIN | G89: CAR. NUEVA PANAMERICANA SUR KM. 29 Z.I. ZONA INDUSTRIAL LURIN - M | H89: MAKITA PERU | I89: 946 422 767 / 950 901 663
B90: 20603065108 | C90: DACA CORPORACION S.A.C. | D90: CERRO COLORADO | E90: AREQUIPA | F90: AREQUIPA | G90: CC Las Malvinas del Sur - Vía Yura Km 9, Arequipa | H90: DACA CORPORACION | I90: 957 770 751 - 994 343 425 | J90: PILAR COSSIO-ADMINISTRADORA | K90: pcossio@daca.pe
B91: 20455576181 | C91: HERRAMIENTAS MINERAS S.R.L. | D91: AREQUIPA | E91: AREQUIPA | F91: CERRO COLORADO | G91: MZA. I LOTE. 5 OTR. ASOCIACION VIVIENDA PERUA | I91: 963701331
B92: 20476580120 | C92: AUTOBEL S.A.C. | D92: LIMA | E92: LIMA | F92: LA VICTORIA | G92: JR. BELGICA NRO. 666 | I92: 998185579
B93: 20603393920 | C93: M&N AQP ELECTROMECANIC EIRL | D93: AREQUIPA | E93: AREQUIPA | F93: AREQUIPA | G93: Urb Cabaña Maria B-8 | I93: 932061604 / 931329873
