Workbook

Sheet Formato de Pedido
P1: [ HERR Y ACC ] ORDEN DE PEDIDO - MAKITA PERU S.A.
O2: Fecha de solicitud : | P2: =TODAY() -> 46220
O3: NRO. ORDEN DEL CLIENTE :
O4: Nro. Pedido SAP :
A6: DATOS DE FACTURACIÓN DEL CLIENTE :
B8: RUC CLIENTE :
B9: CLIENTE : | F9: Baterias XGT-LXT-CXT : | I9: Vigente
B10: DIRECCIÓN FISCAL : | F10: Cargadores XGT-LXT-CXT : | I10: Vigente
F11: Herramientas XGT-LXT-CXT : | I11: Vigente
B12: FORMA Y CONDICION DE PAGO : | F12: OPE y Aspiradoras DC : | I12: Vigente
B13: LETRAS
A15: DATOS DE ENTREGA : (Campo obligatorio)
B17: Despacho en Lima: | E17: Despacho por Agencia (Provincias) :
B18: Entregar en : | F18: Enviar por :
B19: Horario de recepción : | F19: Dirección de agencia :
B20: Persona de contacto : | F20: Destino en provincia :
A22: DETALLE DE PEDIDO :
A24: ITEM | B24: CÓDIGO | C24: DESCRIPCIÓN | D24: PRECIO LISTA UNITARIO | E24: CANT. | F24: DSCTO 1 | G24: DSCTO 2 | I24: DSCTO FINAL | J24: PRECIO SIN IGV | K24: SUB TOTAL SIN DCTOS(A) | L24: SOLES DSCTO 1 (B) | M24: SOLES DSCTO 2 (C) | N24: [STATUS STOCK] | O24: FAMILIA COMERCIAL | P24: Comentarios
A25: 1 | C25: =IFERROR(VLOOKUP(B25,'Lista de Productos'!A:B,2,FALSE)," ") | D25: =IFERROR(VLOOKUP(B25,Tabla_Lista_de_productoss[],5,0),"") | I25: =IFERROR(FIXED(((1-((1-F25%)*(1-G25%)*(1-H25%)))*100),2)," ") -> 0.00 | J25: =IFERROR((E25*(D25*(1-I25%)))," ") | K25: =IFERROR((D25*E25), " ") | L25: =IFERROR((D25*F25%)*E25," ") | M25: =IFERROR(((K25-L25)*G25%), " ") | N25: =IFERROR(VLOOKUP(B25,'Lista de Productos'!A:D,4,FALSE)," ") | O25: =IFERROR(VLOOKUP(B25,'Lista de Productos'!A:C,3,FALSE)," ")
A26: 2 | C26: =IFERROR(VLOOKUP(B26,'Lista de Productos'!A:B,2,FALSE)," ") | D26: =IFERROR(VLOOKUP(B26,Tabla_Lista_de_productoss[],5,0),"") | I26: =IFERROR(FIXED(((1-((1-F26%)*(1-G26%)*(1-H26%)))*100),2)," ") -> 0.00 | J26: =IFERROR((E26*(D26*(1-I26%)))," ") | K26: =IFERROR((D26*E26), " ") | L26: =IFERROR((D26*F26%)*E26," ") | M26: =IFERROR(((K26-L26)*G26%), " ") | N26: =IFERROR(VLOOKUP(B26,'Lista de Productos'!A:D,4,FALSE)," ") | O26: =IFERROR(VLOOKUP(B26,'Lista de Productos'!A:C,3,FALSE)," ")
A27: 3 | C27: =IFERROR(VLOOKUP(B27,'Lista de Productos'!A:B,2,FALSE)," ") | D27: =IFERROR(VLOOKUP(B27,Tabla_Lista_de_productoss[],5,0),"") | I27: =IFERROR(FIXED(((1-((1-F27%)*(1-G27%)*(1-H27%)))*100),2)," ") -> 0.00 | J27: =IFERROR((E27*(D27*(1-I27%)))," ") | K27: =IFERROR((D27*E27), " ") | L27: =IFERROR((D27*F27%)*E27," ") | M27: =IFERROR(((K27-L27)*G27%), " ") | N27: =IFERROR(VLOOKUP(B27,'Lista de Productos'!A:D,4,FALSE)," ") | O27: =IFERROR(VLOOKUP(B27,'Lista de Productos'!A:C,3,FALSE)," ")
A28: 4 | C28: =IFERROR(VLOOKUP(B28,'Lista de Productos'!A:B,2,FALSE)," ") | D28: =IFERROR(VLOOKUP(B28,Tabla_Lista_de_productoss[],5,0),"") | I28: =IFERROR(FIXED(((1-((1-F28%)*(1-G28%)*(1-H28%)))*100),2)," ") -> 0.00 | J28: =IFERROR((E28*(D28*(1-I28%)))," ") | K28: =IFERROR((D28*E28), " ") | L28: =IFERROR((D28*F28%)*E28," ") | M28: =IFERROR(((K28-L28)*G28%), " ") | N28: =IFERROR(VLOOKUP(B28,'Lista de Productos'!A:D,4,FALSE)," ") | O28: =IFERROR(VLOOKUP(B28,'Lista de Productos'!A:C,3,FALSE)," ")
A29: 5 | C29: =IFERROR(VLOOKUP(B29,'Lista de Productos'!A:B,2,FALSE)," ") | D29: =IFERROR(VLOOKUP(B29,Tabla_Lista_de_productoss[],5,0),"") | I29: =IFERROR(FIXED(((1-((1-F29%)*(1-G29%)*(1-H29%)))*100),2)," ") -> 0.00 | J29: =IFERROR((E29*(D29*(1-I29%)))," ") | K29: =IFERROR((D29*E29), " ") | L29: =IFERROR((D29*F29%)*E29," ") | M29: =IFERROR(((K29-L29)*G29%), " ") | N29: =IFERROR(VLOOKUP(B29,'Lista de Productos'!A:D,4,FALSE)," ") | O29: =IFERROR(VLOOKUP(B29,'Lista de Productos'!A:C,3,FALSE)," ")
A30: 6 | C30: =IFERROR(VLOOKUP(B30,'Lista de Productos'!A:B,2,FALSE)," ") | D30: =IFERROR(VLOOKUP(B30,Tabla_Lista_de_productoss[],5,0),"") | I30: =IFERROR(FIXED(((1-((1-F30%)*(1-G30%)*(1-H30%)))*100),2)," ") -> 0.00 | J30: =IFERROR((E30*(D30*(1-I30%)))," ") | K30: =IFERROR((D30*E30), " ") | L30: =IFERROR((D30*F30%)*E30," ") | M30: =IFERROR(((K30-L30)*G30%), " ") | N30: =IFERROR(VLOOKUP(B30,'Lista de Productos'!A:D,4,FALSE)," ") | O30: =IFERROR(VLOOKUP(B30,'Lista de Productos'!A:C,3,FALSE)," ")
A31: 7 | C31: =IFERROR(VLOOKUP(B31,'Lista de Productos'!A:B,2,FALSE)," ") | D31: =IFERROR(VLOOKUP(B31,Tabla_Lista_de_productoss[],5,0),"") | I31: =IFERROR(FIXED(((1-((1-F31%)*(1-G31%)*(1-H31%)))*100),2)," ") -> 0.00 | J31: =IFERROR((E31*(D31*(1-I31%)))," ") | K31: =IFERROR((D31*E31), " ") | L31: =IFERROR((D31*F31%)*E31," ") | M31: =IFERROR(((K31-L31)*G31%), " ") | N31: =IFERROR(VLOOKUP(B31,'Lista de Productos'!A:D,4,FALSE)," ") | O31: =IFERROR(VLOOKUP(B31,'Lista de Productos'!A:C,3,FALSE)," ")
A32: 8 | C32: =IFERROR(VLOOKUP(B32,'Lista de Productos'!A:B,2,FALSE)," ") | D32: =IFERROR(VLOOKUP(B32,Tabla_Lista_de_productoss[],5,0),"") | I32: =IFERROR(FIXED(((1-((1-F32%)*(1-G32%)*(1-H32%)))*100),2)," ") -> 0.00 | J32: =IFERROR((E32*(D32*(1-I32%)))," ") | K32: =IFERROR((D32*E32), " ") | L32: =IFERROR((D32*F32%)*E32," ") | M32: =IFERROR(((K32-L32)*G32%), " ") | N32: =IFERROR(VLOOKUP(B32,'Lista de Productos'!A:D,4,FALSE)," ") | O32: =IFERROR(VLOOKUP(B32,'Lista de Productos'!A:C,3,FALSE)," ")
A33: 9 | C33: =IFERROR(VLOOKUP(B33,'Lista de Productos'!A:B,2,FALSE)," ") | D33: =IFERROR(VLOOKUP(B33,Tabla_Lista_de_productoss[],5,0),"") | I33: =IFERROR(FIXED(((1-((1-F33%)*(1-G33%)*(1-H33%)))*100),2)," ") -> 0.00 | J33: =IFERROR((E33*(D33*(1-I33%)))," ") | K33: =IFERROR((D33*E33), " ") | L33: =IFERROR((D33*F33%)*E33," ") | M33: =IFERROR(((K33-L33)*G33%), " ") | N33: =IFERROR(VLOOKUP(B33,'Lista de Productos'!A:D,4,FALSE)," ") | O33: =IFERROR(VLOOKUP(B33,'Lista de Productos'!A:C,3,FALSE)," ")
A34: 10 | C34: =IFERROR(VLOOKUP(B34,'Lista de Productos'!A:B,2,FALSE)," ") | D34: =IFERROR(VLOOKUP(B34,Tabla_Lista_de_productoss[],5,0),"") | I34: =IFERROR(FIXED(((1-((1-F34%)*(1-G34%)*(1-H34%)))*100),2)," ") -> 0.00 | J34: =IFERROR((E34*(D34*(1-I34%)))," ") | K34: =IFERROR((D34*E34), " ") | L34: =IFERROR((D34*F34%)*E34," ") | M34: =IFERROR(((K34-L34)*G34%), " ") | N34: =IFERROR(VLOOKUP(B34,'Lista de Productos'!A:D,4,FALSE)," ") | O34: =IFERROR(VLOOKUP(B34,'Lista de Productos'!A:C,3,FALSE)," ")
A35: 11 | C35: =IFERROR(VLOOKUP(B35,'Lista de Productos'!A:B,2,FALSE)," ") | D35: =IFERROR(VLOOKUP(B35,Tabla_Lista_de_productoss[],5,0),"") | I35: =IFERROR(FIXED(((1-((1-F35%)*(1-G35%)*(1-H35%)))*100),2)," ") -> 0.00 | J35: =IFERROR((E35*(D35*(1-I35%)))," ") | K35: =IFERROR((D35*E35), " ") | L35: =IFERROR((D35*F35%)*E35," ") | M35: =IFERROR(((K35-L35)*G35%), " ") | N35: =IFERROR(VLOOKUP(B35,'Lista de Productos'!A:D,4,FALSE)," ") | O35: =IFERROR(VLOOKUP(B35,'Lista de Productos'!A:C,3,FALSE)," ")
A36: 12 | C36: =IFERROR(VLOOKUP(B36,'Lista de Productos'!A:B,2,FALSE)," ") | D36: =IFERROR(VLOOKUP(B36,Tabla_Lista_de_productoss[],5,0),"") | I36: =IFERROR(FIXED(((1-((1-F36%)*(1-G36%)*(1-H36%)))*100),2)," ") -> 0.00 | J36: =IFERROR((E36*(D36*(1-I36%)))," ") | K36: =IFERROR((D36*E36), " ") | L36: =IFERROR((D36*F36%)*E36," ") | M36: =IFERROR(((K36-L36)*G36%), " ") | N36: =IFERROR(VLOOKUP(B36,'Lista de Productos'!A:D,4,FALSE)," ") | O36: =IFERROR(VLOOKUP(B36,'Lista de Productos'!A:C,3,FALSE)," ")
A37: 13 | C37: =IFERROR(VLOOKUP(B37,'Lista de Productos'!A:B,2,FALSE)," ") | D37: =IFERROR(VLOOKUP(B37,Tabla_Lista_de_productoss[],5,0),"") | I37: =IFERROR(FIXED(((1-((1-F37%)*(1-G37%)*(1-H37%)))*100),2)," ") -> 0.00 | J37: =IFERROR((E37*(D37*(1-I37%)))," ") | K37: =IFERROR((D37*E37), " ") | L37: =IFERROR((D37*F37%)*E37," ") | M37: =IFERROR(((K37-L37)*G37%), " ") | N37: =IFERROR(VLOOKUP(B37,'Lista de Productos'!A:D,4,FALSE)," ") | O37: =IFERROR(VLOOKUP(B37,'Lista de Productos'!A:C,3,FALSE)," ")
A38: 14 | C38: =IFERROR(VLOOKUP(B38,'Lista de Productos'!A:B,2,FALSE)," ") | D38: =IFERROR(VLOOKUP(B38,Tabla_Lista_de_productoss[],5,0),"") | I38: =IFERROR(FIXED(((1-((1-F38%)*(1-G38%)*(1-H38%)))*100),2)," ") -> 0.00 | J38: =IFERROR((E38*(D38*(1-I38%)))," ") | N38: =IFERROR(VLOOKUP(B38,'Lista de Productos'!A:D,4,FALSE)," ") | O38: =IFERROR(VLOOKUP(B38,'Lista de Productos'!A:C,3,FALSE)," ")
A39: 15 | C39: =IFERROR(VLOOKUP(B39,'Lista de Productos'!A:B,2,FALSE)," ") | D39: =IFERROR(VLOOKUP(B39,Tabla_Lista_de_productoss[],5,0),"") | I39: =IFERROR(FIXED(((1-((1-F39%)*(1-G39%)*(1-H39%)))*100),2)," ") -> 0.00 | J39: =IFERROR((E39*(D39*(1-I39%)))," ") | N39: =IFERROR(VLOOKUP(B39,'Lista de Productos'!A:D,4,FALSE)," ") | O39: =IFERROR(VLOOKUP(B39,'Lista de Productos'!A:C,3,FALSE)," ")
A40: 16 | C40: =IFERROR(VLOOKUP(B40,'Lista de Productos'!A:B,2,FALSE)," ") | D40: =IFERROR(VLOOKUP(B40,Tabla_Lista_de_productoss[],5,0),"") | I40: =IFERROR(FIXED(((1-((1-F40%)*(1-G40%)*(1-H40%)))*100),2)," ") -> 0.00 | J40: =IFERROR((E40*(D40*(1-I40%)))," ") | N40: =IFERROR(VLOOKUP(B40,'Lista de Productos'!A:D,4,FALSE)," ") | O40: =IFERROR(VLOOKUP(B40,'Lista de Productos'!A:C,3,FALSE)," ")
A41: 17 | C41: =IFERROR(VLOOKUP(B41,'Lista de Productos'!A:B,2,FALSE)," ") | D41: =IFERROR(VLOOKUP(B41,Tabla_Lista_de_productoss[],5,0),"") | I41: =IFERROR(FIXED(((1-((1-F41%)*(1-G41%)*(1-H41%)))*100),2)," ") -> 0.00 | J41: =IFERROR((E41*(D41*(1-I41%)))," ") | N41: =IFERROR(VLOOKUP(B41,'Lista de Productos'!A:D,4,FALSE)," ") | O41: =IFERROR(VLOOKUP(B41,'Lista de Productos'!A:C,3,FALSE)," ")
A42: 18 | C42: =IFERROR(VLOOKUP(B42,'Lista de Productos'!A:B,2,FALSE)," ") | D42: =IFERROR(VLOOKUP(B42,Tabla_Lista_de_productoss[],5,0),"") | I42: =IFERROR(FIXED(((1-((1-F42%)*(1-G42%)*(1-H42%)))*100),2)," ") -> 0.00 | J42: =IFERROR((E42*(D42*(1-I42%)))," ") | N42: =IFERROR(VLOOKUP(B42,'Lista de Productos'!A:D,4,FALSE)," ") | O42: =IFERROR(VLOOKUP(B42,'Lista de Productos'!A:C,3,FALSE)," ")
A43: 19 | C43: =IFERROR(VLOOKUP(B43,'Lista de Productos'!A:B,2,FALSE)," ") | D43: =IFERROR(VLOOKUP(B43,Tabla_Lista_de_productoss[],5,0),"") | I43: =IFERROR(FIXED(((1-((1-F43%)*(1-G43%)*(1-H43%)))*100),2)," ") -> 0.00 | J43: =IFERROR((E43*(D43*(1-I43%)))," ") | N43: =IFERROR(VLOOKUP(B43,'Lista de Productos'!A:D,4,FALSE)," ") | O43: =IFERROR(VLOOKUP(B43,'Lista de Productos'!A:C,3,FALSE)," ")
A44: 20 | C44: =IFERROR(VLOOKUP(B44,'Lista de Productos'!A:B,2,FALSE)," ") | D44: =IFERROR(VLOOKUP(B44,Tabla_Lista_de_productoss[],5,0),"") | I44: =IFERROR(FIXED(((1-((1-F44%)*(1-G44%)*(1-H44%)))*100),2)," ") -> 0.00 | J44: =IFERROR((E44*(D44*(1-I44%)))," ") | N44: =IFERROR(VLOOKUP(B44,'Lista de Productos'!A:D,4,FALSE)," ") | O44: =IFERROR(VLOOKUP(B44,'Lista de Productos'!A:C,3,FALSE)," ")
A45: 21 | C45: =IFERROR(VLOOKUP(B45,'Lista de Productos'!A:B,2,FALSE)," ") | D45: =IFERROR(VLOOKUP(B45,Tabla_Lista_de_productoss[],5,0),"") | I45: =IFERROR(FIXED(((1-((1-F45%)*(1-G45%)*(1-H45%)))*100),2)," ") -> 0.00 | J45: =IFERROR((E45*(D45*(1-I45%)))," ") | N45: =IFERROR(VLOOKUP(B45,'Lista de Productos'!A:D,4,FALSE)," ") | O45: =IFERROR(VLOOKUP(B45,'Lista de Productos'!A:C,3,FALSE)," ")
A46: 22 | C46: =IFERROR(VLOOKUP(B46,'Lista de Productos'!A:B,2,FALSE)," ") | D46: =IFERROR(VLOOKUP(B46,Tabla_Lista_de_productoss[],5,0),"") | I46: =IFERROR(FIXED(((1-((1-F46%)*(1-G46%)*(1-H46%)))*100),2)," ") -> 0.00 | J46: =IFERROR((E46*(D46*(1-I46%)))," ") | N46: =IFERROR(VLOOKUP(B46,'Lista de Productos'!A:D,4,FALSE)," ") | O46: =IFERROR(VLOOKUP(B46,'Lista de Productos'!A:C,3,FALSE)," ")
A47: 23 | C47: =IFERROR(VLOOKUP(B47,'Lista de Productos'!A:B,2,FALSE)," ") | D47: =IFERROR(VLOOKUP(B47,Tabla_Lista_de_productoss[],5,0),"") | I47: =IFERROR(FIXED(((1-((1-F47%)*(1-G47%)*(1-H47%)))*100),2)," ") -> 0.00 | J47: =IFERROR((E47*(D47*(1-I47%)))," ") | N47: =IFERROR(VLOOKUP(B47,'Lista de Productos'!A:D,4,FALSE)," ") | O47: =IFERROR(VLOOKUP(B47,'Lista de Productos'!A:C,3,FALSE)," ")
A48: 24 | C48: =IFERROR(VLOOKUP(B48,'Lista de Productos'!A:B,2,FALSE)," ") | D48: =IFERROR(VLOOKUP(B48,Tabla_Lista_de_productoss[],5,0),"") | I48: =IFERROR(FIXED(((1-((1-F48%)*(1-G48%)*(1-H48%)))*100),2)," ") -> 0.00 | J48: =IFERROR((E48*(D48*(1-I48%)))," ") | N48: =IFERROR(VLOOKUP(B48,'Lista de Productos'!A:D,4,FALSE)," ") | O48: =IFERROR(VLOOKUP(B48,'Lista de Productos'!A:C,3,FALSE)," ")
A49: 25 | C49: =IFERROR(VLOOKUP(B49,'Lista de Productos'!A:B,2,FALSE)," ") | D49: =IFERROR(VLOOKUP(B49,Tabla_Lista_de_productoss[],5,0),"") | I49: =IFERROR(FIXED(((1-((1-F49%)*(1-G49%)*(1-H49%)))*100),2)," ") -> 0.00 | J49: =IFERROR((E49*(D49*(1-I49%)))," ") | N49: =IFERROR(VLOOKUP(B49,'Lista de Productos'!A:D,4,FALSE)," ") | O49: =IFERROR(VLOOKUP(B49,'Lista de Productos'!A:C,3,FALSE)," ")
A50: 26 | C50: =IFERROR(VLOOKUP(B50,'Lista de Productos'!A:B,2,FALSE)," ") | D50: =IFERROR(VLOOKUP(B50,Tabla_Lista_de_productoss[],5,0),"") | I50: =IFERROR(FIXED(((1-((1-F50%)*(1-G50%)*(1-H50%)))*100),2)," ") -> 0.00 | J50: =IFERROR((E50*(D50*(1-I50%)))," ") | K50: =IFERROR((D50*E50), " ") | L50: =IFERROR((D50*F50%)*E50," ") | M50: =IFERROR(((K50-L50)*G50%), " ") | N50: =IFERROR(VLOOKUP(B50,'Lista de Productos'!A:D,4,FALSE)," ") | O50: =IFERROR(VLOOKUP(B50,'Lista de Productos'!A:C,3,FALSE)," ")
A51: 27 | C51: =IFERROR(VLOOKUP(B51,'Lista de Productos'!A:B,2,FALSE)," ") | D51: =IFERROR(VLOOKUP(B51,Tabla_Lista_de_productoss[],5,0),"") | I51: =IFERROR(FIXED(((1-((1-F51%)*(1-G51%)*(1-H51%)))*100),2)," ") -> 0.00 | J51: =IFERROR((E51*(D51*(1-I51%)))," ") | K51: =IFERROR((D51*E51), " ") | L51: =IFERROR((D51*F51%)*E51," ") | M51: =IFERROR(((K51-L51)*G51%), " ") | N51: =IFERROR(VLOOKUP(B51,'Lista de Productos'!A:D,4,FALSE)," ") | O51: =IFERROR(VLOOKUP(B51,'Lista de Productos'!A:C,3,FALSE)," ")
A52: 28 | C52: =IFERROR(VLOOKUP(B52,'Lista de Productos'!A:B,2,FALSE)," ") | D52: =IFERROR(VLOOKUP(B52,Tabla_Lista_de_productoss[],5,0),"") | I52: =IFERROR(FIXED(((1-((1-F52%)*(1-G52%)*(1-H52%)))*100),2)," ") -> 0.00 | J52: =IFERROR((E52*(D52*(1-I52%)))," ") | N52: =IFERROR(VLOOKUP(B52,'Lista de Productos'!A:D,4,FALSE)," ") | O52: =IFERROR(VLOOKUP(B52,'Lista de Productos'!A:C,3,FALSE)," ")
A53: 29 | C53: =IFERROR(VLOOKUP(B53,'Lista de Productos'!A:B,2,FALSE)," ") | D53: =IFERROR(VLOOKUP(B53,Tabla_Lista_de_productoss[],5,0),"") | I53: =IFERROR(FIXED(((1-((1-F53%)*(1-G53%)*(1-H53%)))*100),2)," ") -> 0.00 | J53: =IFERROR((E53*(D53*(1-I53%)))," ") | N53: =IFERROR(VLOOKUP(B53,'Lista de Productos'!A:D,4,FALSE)," ") | O53: =IFERROR(VLOOKUP(B53,'Lista de Productos'!A:C,3,FALSE)," ")
A54: 30 | C54: =IFERROR(VLOOKUP(B54,'Lista de Productos'!A:B,2,FALSE)," ") | D54: =IFERROR(VLOOKUP(B54,Tabla_Lista_de_productoss[],5,0),"") | I54: =IFERROR(FIXED(((1-((1-F54%)*(1-G54%)*(1-H54%)))*100),2)," ") -> 0.00 | J54: =IFERROR((E54*(D54*(1-I54%)))," ") | N54: =IFERROR(VLOOKUP(B54,'Lista de Productos'!A:D,4,FALSE)," ") | O54: =IFERROR(VLOOKUP(B54,'Lista de Productos'!A:C,3,FALSE)," ")
A55: 31 | C55: =IFERROR(VLOOKUP(B55,'Lista de Productos'!A:B,2,FALSE)," ") | D55: =IFERROR(VLOOKUP(B55,Tabla_Lista_de_productoss[],5,0),"") | I55: =IFERROR(FIXED(((1-((1-F55%)*(1-G55%)*(1-H55%)))*100),2)," ") -> 0.00 | J55: =IFERROR((E55*(D55*(1-I55%)))," ") | N55: =IFERROR(VLOOKUP(B55,'Lista de Productos'!A:D,4,FALSE)," ") | O55: =IFERROR(VLOOKUP(B55,'Lista de Productos'!A:C,3,FALSE)," ")
A56: 32 | C56: =IFERROR(VLOOKUP(B56,'Lista de Productos'!A:B,2,FALSE)," ") | D56: =IFERROR(VLOOKUP(B56,Tabla_Lista_de_productoss[],5,0),"") | I56: =IFERROR(FIXED(((1-((1-F56%)*(1-G56%)*(1-H56%)))*100),2)," ") -> 0.00 | J56: =IFERROR((E56*(D56*(1-I56%)))," ") | N56: =IFERROR(VLOOKUP(B56,'Lista de Productos'!A:D,4,FALSE)," ") | O56: =IFERROR(VLOOKUP(B56,'Lista de Productos'!A:C,3,FALSE)," ")
A57: 33 | C57: =IFERROR(VLOOKUP(B57,'Lista de Productos'!A:B,2,FALSE)," ") | D57: =IFERROR(VLOOKUP(B57,Tabla_Lista_de_productoss[],5,0),"") | I57: =IFERROR(FIXED(((1-((1-F57%)*(1-G57%)*(1-H57%)))*100),2)," ") -> 0.00 | J57: =IFERROR((E57*(D57*(1-I57%)))," ") | N57: =IFERROR(VLOOKUP(B57,'Lista de Productos'!A:D,4,FALSE)," ") | O57: =IFERROR(VLOOKUP(B57,'Lista de Productos'!A:C,3,FALSE)," ")
A58: 34 | C58: =IFERROR(VLOOKUP(B58,'Lista de Productos'!A:B,2,FALSE)," ") | D58: =IFERROR(VLOOKUP(B58,Tabla_Lista_de_productoss[],5,0),"") | I58: =IFERROR(FIXED(((1-((1-F58%)*(1-G58%)*(1-H58%)))*100),2)," ") -> 0.00 | J58: =IFERROR((E58*(D58*(1-I58%)))," ") | N58: =IFERROR(VLOOKUP(B58,'Lista de Productos'!A:D,4,FALSE)," ") | O58: =IFERROR(VLOOKUP(B58,'Lista de Productos'!A:C,3,FALSE)," ")
A59: 35 | C59: =IFERROR(VLOOKUP(B59,'Lista de Productos'!A:B,2,FALSE)," ") | D59: =IFERROR(VLOOKUP(B59,Tabla_Lista_de_productoss[],5,0),"") | I59: =IFERROR(FIXED(((1-((1-F59%)*(1-G59%)*(1-H59%)))*100),2)," ") -> 0.00 | J59: =IFERROR((E59*(D59*(1-I59%)))," ") | N59: =IFERROR(VLOOKUP(B59,'Lista de Productos'!A:D,4,FALSE)," ") | O59: =IFERROR(VLOOKUP(B59,'Lista de Productos'!A:C,3,FALSE)," ")
A60: 36 | C60: =IFERROR(VLOOKUP(B60,'Lista de Productos'!A:B,2,FALSE)," ") | D60: =IFERROR(VLOOKUP(B60,Tabla_Lista_de_productoss[],5,0),"") | I60: =IFERROR(FIXED(((1-((1-F60%)*(1-G60%)*(1-H60%)))*100),2)," ") -> 0.00 | J60: =IFERROR((E60*(D60*(1-I60%)))," ") | N60: =IFERROR(VLOOKUP(B60,'Lista de Productos'!A:D,4,FALSE)," ") | O60: =IFERROR(VLOOKUP(B60,'Lista de Productos'!A:C,3,FALSE)," ")
A61: 37 | C61: =IFERROR(VLOOKUP(B61,'Lista de Productos'!A:B,2,FALSE)," ") | D61: =IFERROR(VLOOKUP(B61,Tabla_Lista_de_productoss[],5,0),"") | I61: =IFERROR(FIXED(((1-((1-F61%)*(1-G61%)*(1-H61%)))*100),2)," ") -> 0.00 | J61: =IFERROR((E61*(D61*(1-I61%)))," ") | N61: =IFERROR(VLOOKUP(B61,'Lista de Productos'!A:D,4,FALSE)," ") | O61: =IFERROR(VLOOKUP(B61,'Lista de Productos'!A:C,3,FALSE)," ")
A62: 38 | C62: =IFERROR(VLOOKUP(B62,'Lista de Productos'!A:B,2,FALSE)," ") | D62: =IFERROR(VLOOKUP(B62,Tabla_Lista_de_productoss[],5,0),"") | I62: =IFERROR(FIXED(((1-((1-F62%)*(1-G62%)*(1-H62%)))*100),2)," ") -> 0.00 | J62: =IFERROR((E62*(D62*(1-I62%)))," ") | K62: =IFERROR((D62*E62), " ") | L62: =IFERROR((D62*F62%)*E62," ") | M62: =IFERROR(((K62-L62)*G62%), " ") | N62: =IFERROR(VLOOKUP(B62,'Lista de Productos'!A:D,4,FALSE)," ") | O62: =IFERROR(VLOOKUP(B62,'Lista de Productos'!A:C,3,FALSE)," ")
A63: 39 | C63: =IFERROR(VLOOKUP(B63,'Lista de Productos'!A:B,2,FALSE)," ") | D63: =IFERROR(VLOOKUP(B63,Tabla_Lista_de_productoss[],5,0),"") | I63: =IFERROR(FIXED(((1-((1-F63%)*(1-G63%)*(1-H63%)))*100),2)," ") -> 0.00 | J63: =IFERROR((E63*(D63*(1-I63%)))," ") | K63: =IFERROR((D63*E63), " ") | L63: =IFERROR((D63*F63%)*E63," ") | M63: =IFERROR(((K63-L63)*G63%), " ") | N63: =IFERROR(VLOOKUP(B63,'Lista de Productos'!A:D,4,FALSE)," ") | O63: =IFERROR(VLOOKUP(B63,'Lista de Productos'!A:C,3,FALSE)," ")
A64: 40 | C64: =IFERROR(VLOOKUP(B64,'Lista de Productos'!A:B,2,FALSE)," ") | D64: =IFERROR(VLOOKUP(B64,Tabla_Lista_de_productoss[],5,0),"") | I64: =IFERROR(FIXED(((1-((1-F64%)*(1-G64%)*(1-H64%)))*100),2)," ") -> 0.00 | N64: =IFERROR(VLOOKUP(B64,'Lista de Productos'!A:D,4,FALSE)," ") | O64: =IFERROR(VLOOKUP(B64,'Lista de Productos'!A:C,3,FALSE)," ")
A65: 41 | C65: =IFERROR(VLOOKUP(B65,'Lista de Productos'!A:B,2,FALSE)," ") | D65: =IFERROR(VLOOKUP(B65,Tabla_Lista_de_productoss[],5,0),"") | I65: =IFERROR(FIXED(((1-((1-F65%)*(1-G65%)*(1-H65%)))*100),2)," ") -> 0.00 | N65: =IFERROR(VLOOKUP(B65,'Lista de Productos'!A:D,4,FALSE)," ") | O65: =IFERROR(VLOOKUP(B65,'Lista de Productos'!A:C,3,FALSE)," ")
A66: 42 | C66: =IFERROR(VLOOKUP(B66,'Lista de Productos'!A:B,2,FALSE)," ") | D66: =IFERROR(VLOOKUP(B66,Tabla_Lista_de_productoss[],5,0),"") | I66: =IFERROR(FIXED(((1-((1-F66%)*(1-G66%)*(1-H66%)))*100),2)," ") -> 0.00 | N66: =IFERROR(VLOOKUP(B66,'Lista de Productos'!A:D,4,FALSE)," ") | O66: =IFERROR(VLOOKUP(B66,'Lista de Productos'!A:C,3,FALSE)," ")
A67: 43 | C67: =IFERROR(VLOOKUP(B67,'Lista de Productos'!A:B,2,FALSE)," ") | D67: =IFERROR(VLOOKUP(B67,Tabla_Lista_de_productoss[],5,0),"") | I67: =IFERROR(FIXED(((1-((1-F67%)*(1-G67%)*(1-H67%)))*100),2)," ") -> 0.00 | N67: =IFERROR(VLOOKUP(B67,'Lista de Productos'!A:D,4,FALSE)," ") | O67: =IFERROR(VLOOKUP(B67,'Lista de Productos'!A:C,3,FALSE)," ")
A68: 44 | C68: =IFERROR(VLOOKUP(B68,'Lista de Productos'!A:B,2,FALSE)," ") | D68: =IFERROR(VLOOKUP(B68,Tabla_Lista_de_productoss[],5,0),"") | I68: =IFERROR(FIXED(((1-((1-F68%)*(1-G68%)*(1-H68%)))*100),2)," ") -> 0.00 | N68: =IFERROR(VLOOKUP(B68,'Lista de Productos'!A:D,4,FALSE)," ") | O68: =IFERROR(VLOOKUP(B68,'Lista de Productos'!A:C,3,FALSE)," ")
A69: 45 | C69: =IFERROR(VLOOKUP(B69,'Lista de Productos'!A:B,2,FALSE)," ") | D69: =IFERROR(VLOOKUP(B69,Tabla_Lista_de_productoss[],5,0),"") | I69: =IFERROR(FIXED(((1-((1-F69%)*(1-G69%)*(1-H69%)))*100),2)," ") -> 0.00 | N69: =IFERROR(VLOOKUP(B69,'Lista de Productos'!A:D,4,FALSE)," ") | O69: =IFERROR(VLOOKUP(B69,'Lista de Productos'!A:C,3,FALSE)," ")
A70: 46 | C70: =IFERROR(VLOOKUP(B70,'Lista de Productos'!A:B,2,FALSE)," ") | D70: =IFERROR(VLOOKUP(B70,Tabla_Lista_de_productoss[],5,0),"") | I70: =IFERROR(FIXED(((1-((1-F70%)*(1-G70%)*(1-H70%)))*100),2)," ") -> 0.00 | N70: =IFERROR(VLOOKUP(B70,'Lista de Productos'!A:D,4,FALSE)," ") | O70: =IFERROR(VLOOKUP(B70,'Lista de Productos'!A:C,3,FALSE)," ")
A71: 47 | C71: =IFERROR(VLOOKUP(B71,'Lista de Productos'!A:B,2,FALSE)," ") | D71: =IFERROR(VLOOKUP(B71,Tabla_Lista_de_productoss[],5,0),"") | I71: =IFERROR(FIXED(((1-((1-F71%)*(1-G71%)*(1-H71%)))*100),2)," ") -> 0.00 | N71: =IFERROR(VLOOKUP(B71,'Lista de Productos'!A:D,4,FALSE)," ") | O71: =IFERROR(VLOOKUP(B71,'Lista de Productos'!A:C,3,FALSE)," ")
A72: 48 | C72: =IFERROR(VLOOKUP(B72,'Lista de Productos'!A:B,2,FALSE)," ") | D72: =IFERROR(VLOOKUP(B72,Tabla_Lista_de_productoss[],5,0),"") | I72: =IFERROR(FIXED(((1-((1-F72%)*(1-G72%)*(1-H72%)))*100),2)," ") -> 0.00 | N72: =IFERROR(VLOOKUP(B72,'Lista de Productos'!A:D,4,FALSE)," ") | O72: =IFERROR(VLOOKUP(B72,'Lista de Productos'!A:C,3,FALSE)," ")
A73: 49 | C73: =IFERROR(VLOOKUP(B73,'Lista de Productos'!A:B,2,FALSE)," ") | D73: =IFERROR(VLOOKUP(B73,Tabla_Lista_de_productoss[],5,0),"") | I73: =IFERROR(FIXED(((1-((1-F73%)*(1-G73%)*(1-H73%)))*100),2)," ") -> 0.00 | N73: =IFERROR(VLOOKUP(B73,'Lista de Productos'!A:D,4,FALSE)," ") | O73: =IFERROR(VLOOKUP(B73,'Lista de Productos'!A:C,3,FALSE)," ")
A74: 50 | C74: =IFERROR(VLOOKUP(B74,'Lista de Productos'!A:B,2,FALSE)," ") | D74: =IFERROR(VLOOKUP(B74,Tabla_Lista_de_productoss[],5,0),"") | I74: =IFERROR(FIXED(((1-((1-F74%)*(1-G74%)*(1-H74%)))*100),2)," ") -> 0.00 | N74: =IFERROR(VLOOKUP(B74,'Lista de Productos'!A:D,4,FALSE)," ") | O74: =IFERROR(VLOOKUP(B74,'Lista de Productos'!A:C,3,FALSE)," ")
A75: 51 | C75: =IFERROR(VLOOKUP(B75,'Lista de Productos'!A:B,2,FALSE)," ") | D75: =IFERROR(VLOOKUP(B75,Tabla_Lista_de_productoss[],5,0),"") | I75: =IFERROR(FIXED(((1-((1-F75%)*(1-G75%)*(1-H75%)))*100),2)," ") -> 0.00 | N75: =IFERROR(VLOOKUP(B75,'Lista de Productos'!A:D,4,FALSE)," ") | O75: =IFERROR(VLOOKUP(B75,'Lista de Productos'!A:C,3,FALSE)," ")
... A79: 55 | C79: =IFERROR(VLOOKUP(B79,'Lista de Productos'!A:B,2,FALSE)," ") | D79: =IFERROR(VLOOKUP(B79,Tabla_Lista_de_productoss[],5,0),"") | I79: =IFERROR(FIXED(((1-((1-F79%)*(1-G79%)*(1-H79%)))*100),2)," ") -> 0.00 | N79: =IFERROR(VLOOKUP(B79,'Lista de Productos'!A:D,4,FALSE)," ") | O79: =IFERROR(VLOOKUP(B79,'Lista de Productos'!A:C,3,FALSE)," ")
A80: 56 | C80: =IFERROR(VLOOKUP(B80,'Lista de Productos'!A:B,2,FALSE)," ") | D80: =IFERROR(VLOOKUP(B80,Tabla_Lista_de_productoss[],5,0),"") | I80: =IFERROR(FIXED(((1-((1-F80%)*(1-G80%)*(1-H80%)))*100),2)," ") -> 0.00 | J80: =IFERROR((E80*(D80*(1-I80%)))," ") | K80: =IFERROR((D80*E80), " ") | L80: =IFERROR((D80*F80%)*E80," ") | M80: =IFERROR(((K80-L80)*G80%), " ") | N80: =IFERROR(VLOOKUP(B80,'Lista de Productos'!A:D,4,FALSE)," ") | O80: =IFERROR(VLOOKUP(B80,'Lista de Productos'!A:C,3,FALSE)," ")
A81: 57 | C81: =IFERROR(VLOOKUP(B81,'Lista de Productos'!A:B,2,FALSE)," ") | D81: =IFERROR(VLOOKUP(B81,Tabla_Lista_de_productoss[],5,0),"") | I81: =IFERROR(FIXED(((1-((1-F81%)*(1-G81%)*(1-H81%)))*100),2)," ") -> 0.00 | N81: =IFERROR(VLOOKUP(B81,'Lista de Productos'!A:D,4,FALSE)," ") | O81: =IFERROR(VLOOKUP(B81,'Lista de Productos'!A:C,3,FALSE)," ")
A82: 58 | C82: =IFERROR(VLOOKUP(B82,'Lista de Productos'!A:B,2,FALSE)," ") | D82: =IFERROR(VLOOKUP(B82,Tabla_Lista_de_productoss[],5,0),"") | I82: =IFERROR(FIXED(((1-((1-F82%)*(1-G82%)*(1-H82%)))*100),2)," ") -> 0.00 | N82: =IFERROR(VLOOKUP(B82,'Lista de Productos'!A:D,4,FALSE)," ") | O82: =IFERROR(VLOOKUP(B82,'Lista de Productos'!A:C,3,FALSE)," ")
A83: 59 | C83: =IFERROR(VLOOKUP(B83,'Lista de Productos'!A:B,2,FALSE)," ") | D83: =IFERROR(VLOOKUP(B83,Tabla_Lista_de_productoss[],5,0),"") | I83: =IFERROR(FIXED(((1-((1-F83%)*(1-G83%)*(1-H83%)))*100),2)," ") -> 0.00 | N83: =IFERROR(VLOOKUP(B83,'Lista de Productos'!A:D,4,FALSE)," ") | O83: =IFERROR(VLOOKUP(B83,'Lista de Productos'!A:C,3,FALSE)," ")
A84: 60 | C84: =IFERROR(VLOOKUP(B84,'Lista de Productos'!A:B,2,FALSE)," ") | D84: =IFERROR(VLOOKUP(B84,Tabla_Lista_de_productoss[],5,0),"") | I84: =IFERROR(FIXED(((1-((1-F84%)*(1-G84%)*(1-H84%)))*100),2)," ") -> 0.00 | N84: =IFERROR(VLOOKUP(B84,'Lista de Productos'!A:D,4,FALSE)," ") | O84: =IFERROR(VLOOKUP(B84,'Lista de Productos'!A:C,3,FALSE)," ")
A85: 61 | C85: =IFERROR(VLOOKUP(B85,'Lista de Productos'!A:B,2,FALSE)," ") | D85: =IFERROR(VLOOKUP(B85,Tabla_Lista_de_productoss[],5,0),"") | I85: =IFERROR(FIXED(((1-((1-F85%)*(1-G85%)*(1-H85%)))*100),2)," ") -> 0.00 | N85: =IFERROR(VLOOKUP(B85,'Lista de Productos'!A:D,4,FALSE)," ") | O85: =IFERROR(VLOOKUP(B85,'Lista de Productos'!A:C,3,FALSE)," ")
A86: 62 | C86: =IFERROR(VLOOKUP(B86,'Lista de Productos'!A:B,2,FALSE)," ") | D86: =IFERROR(VLOOKUP(B86,Tabla_Lista_de_productoss[],5,0),"") | I86: =IFERROR(FIXED(((1-((1-F86%)*(1-G86%)*(1-H86%)))*100),2)," ") -> 0.00 | N86: =IFERROR(VLOOKUP(B86,'Lista de Productos'!A:D,4,FALSE)," ") | O86: =IFERROR(VLOOKUP(B86,'Lista de Productos'!A:C,3,FALSE)," ")
A87: 63 | C87: =IFERROR(VLOOKUP(B87,'Lista de Productos'!A:B,2,FALSE)," ") | D87: =IFERROR(VLOOKUP(B87,Tabla_Lista_de_productoss[],5,0),"") | I87: =IFERROR(FIXED(((1-((1-F87%)*(1-G87%)*(1-H87%)))*100),2)," ") -> 0.00 | N87: =IFERROR(VLOOKUP(B87,'Lista de Productos'!A:D,4,FALSE)," ") | O87: =IFERROR(VLOOKUP(B87,'Lista de Productos'!A:C,3,FALSE)," ")
A88: 64 | C88: =IFERROR(VLOOKUP(B88,'Lista de Productos'!A:B,2,FALSE)," ") | D88: =IFERROR(VLOOKUP(B88,Tabla_Lista_de_productoss[],5,0),"") | I88: =IFERROR(FIXED(((1-((1-F88%)*(1-G88%)*(1-H88%)))*100),2)," ") -> 0.00 | J88: =IFERROR((E88*(D88*(1-I88%)))," ") | K88: =IFERROR((D88*E88), " ") | L88: =IFERROR((D88*F88%)*E88," ") | M88: =IFERROR(((K88-L88)*G88%), " ") | N88: =IFERROR(VLOOKUP(B88,'Lista de Productos'!A:D,4,FALSE)," ") | O88: =IFERROR(VLOOKUP(B88,'Lista de Productos'!A:C,3,FALSE)," ")
A89: 65 | C89: =IFERROR(VLOOKUP(B89,'Lista de Productos'!A:B,2,FALSE)," ") | D89: =IFERROR(VLOOKUP(B89,Tabla_Lista_de_productoss[],5,0),"") | I89: =IFERROR(FIXED(((1-((1-F89%)*(1-G89%)*(1-H89%)))*100),2)," ") -> 0.00 | J89: =IFERROR((E89*(D89*(1-I89%)))," ") | K89: =IFERROR((D89*E89), " ") | L89: =IFERROR((D89*F89%)*E89," ") | M89: =IFERROR(((K89-L89)*G89%), " ") | N89: =IFERROR(VLOOKUP(B89,'Lista de Productos'!A:D,4,FALSE)," ") | O89: =IFERROR(VLOOKUP(B89,'Lista de Productos'!A:C,3,FALSE)," ")
A90: 66 | C90: =IFERROR(VLOOKUP(B90,'Lista de Productos'!A:B,2,FALSE)," ") | D90: =IFERROR(VLOOKUP(B90,Tabla_Lista_de_productoss[],5,0),"") | I90: =IFERROR(FIXED(((1-((1-F90%)*(1-G90%)*(1-H90%)))*100),2)," ") -> 0.00 | J90: =IFERROR((E90*(D90*(1-I90%)))," ") | K90: =IFERROR((D90*E90), " ") | L90: =IFERROR((D90*F90%)*E90," ") | M90: =IFERROR(((K90-L90)*G90%), " ") | N90: =IFERROR(VLOOKUP(B90,'Lista de Productos'!A:D,4,FALSE)," ") | O90: =IFERROR(VLOOKUP(B90,'Lista de Productos'!A:C,3,FALSE)," ")
A91: 67 | C91: =IFERROR(VLOOKUP(B91,'Lista de Productos'!A:B,2,FALSE)," ") | D91: =IFERROR(VLOOKUP(B91,Tabla_Lista_de_productoss[],5,0),"") | I91: =IFERROR(FIXED(((1-((1-F91%)*(1-G91%)*(1-H91%)))*100),2)," ") -> 0.00 | J91: =IFERROR((E91*(D91*(1-I91%)))," ") | K91: =IFERROR((D91*E91), " ") | L91: =IFERROR((D91*F91%)*E91," ") | M91: =IFERROR(((K91-L91)*G91%), " ") | N91: =IFERROR(VLOOKUP(B91,'Lista de Productos'!A:D,4,FALSE)," ") | O91: =IFERROR(VLOOKUP(B91,'Lista de Productos'!A:C,3,FALSE)," ")
A92: 68 | C92: =IFERROR(VLOOKUP(B92,'Lista de Productos'!A:B,2,FALSE)," ") | D92: =IFERROR(VLOOKUP(B92,Tabla_Lista_de_productoss[],5,0),"") | I92: =IFERROR(FIXED(((1-((1-F92%)*(1-G92%)*(1-H92%)))*100),2)," ") -> 0.00 | J92: =IFERROR((E92*(D92*(1-I92%)))," ") | K92: =IFERROR((D92*E92), " ") | L92: =IFERROR((D92*F92%)*E92," ") | M92: =IFERROR(((K92-L92)*G92%), " ") | N92: =IFERROR(VLOOKUP(B92,'Lista de Productos'!A:D,4,FALSE)," ") | O92: =IFERROR(VLOOKUP(B92,'Lista de Productos'!A:C,3,FALSE)," ")
A93: 69 | C93: =IFERROR(VLOOKUP(B93,'Lista de Productos'!A:B,2,FALSE)," ") | D93: =IFERROR(VLOOKUP(B93,Tabla_Lista_de_productoss[],5,0),"") | I93: =IFERROR(FIXED(((1-((1-F93%)*(1-G93%)*(1-H93%)))*100),2)," ") -> 0.00 | J93: =IFERROR((E93*(D93*(1-I93%)))," ") | K93: =IFERROR((D93*E93), " ") | L93: =IFERROR((D93*F93%)*E93," ") | M93: =IFERROR(((K93-L93)*G93%), " ") | N93: =IFERROR(VLOOKUP(B93,'Lista de Productos'!A:D,4,FALSE)," ") | O93: =IFERROR(VLOOKUP(B93,'Lista de Productos'!A:C,3,FALSE)," ")
A94: 70 | C94: =IFERROR(VLOOKUP(B94,'Lista de Productos'!A:B,2,FALSE)," ") | D94: =IFERROR(VLOOKUP(B94,Tabla_Lista_de_productoss[],5,0),"") | I94: =IFERROR(FIXED(((1-((1-F94%)*(1-G94%)*(1-H94%)))*100),2)," ") -> 0.00 | J94: =IFERROR((E94*(D94*(1-I94%)))," ") | K94: =IFERROR((D94*E94), " ") | L94: =IFERROR((D94*F94%)*E94," ") | M94: =IFERROR(((K94-L94)*G94%), " ") | N94: =IFERROR(VLOOKUP(B94,'Lista de Productos'!A:D,4,FALSE)," ") | O94: =IFERROR(VLOOKUP(B94,'Lista de Productos'!A:C,3,FALSE)," ")
B96: MERCHANDISING Y OBSEQUIOS PUBLICITARIOS | F96: SUB TOTAL SIN DCTOS (A) | J96: =+SUM(K25:K94) -> 0
B97: CÓDIGO | C97: DESCRIPCIÓN | D97: CANT. | F97: DESCUENTO 1 (B) | J97: =+SUM(L25:L94) -> 0 | O97: [STATUS STOCK]
F98: DESCUENTO 2 (C) | I98: =IFERROR((J98/(J96-J97)),"") | J98: =+SUM(M25:M94) -> 0 | O98: Rojo | P98: Agotado
F99: BASE IMPONIBLE | J99: =SUM(J25:J94) -> 0 | O99: Morado | P99: De 1 a 10 und
F100: IGV 18% | J100: =J99*0.18 -> 0 | O100: Amarillo | P100: De 11 a 50 und
F101: TOTAL CON IGV | J101: =+J99+J100 -> 0 | O101: Azul | P101: De 51 a 100 und
O102: Verde | P102: De 101 a más und
B103: REVISA MERCH VIGENTE AQUÍ | F103: SALDO A FAVOR DEL CLIENTE | G103: SALDO A FAVOR | J103: 0 | O103: *Consultar stock de COMBOS con ATC / Vendedor
A104: (1) Makita Perú S.A. no se responsabiliza por retrasos en la entrega si el cliente no completa correctamente los datos de entrega. | F104: MONTO A ABONAR | G104: SALDO A FAVOR | J104: =J101-J103 -> 0
A105: (2) Lista de precios actualizado a Enero 2022. Precios y promociones pueden variar sin previo aviso.

Sheet PROMO
A1: COD. ARTICULO | B1: DESCRIPCION | C1: LISTA GENERAL | D1: FAMILIA SAP | E1: Column5 | F1: Column6
A2: DLM330Z-3.0 | B2: DLM330Z(x1) + 632G12-3(x1) + 630718-5(x1) | C2: 1185.5932 | D2: PROMOCIONES | F2: OPELXT MG LISTA 2
A3: DLM330Z-6.0 | B3: DLM330Z(x1) + 632F69-8(x1) + 630718-5(x1) | C3: 1312.7119 | D3: PROMOCIONES
A4: DUR192LSF-3.0 | B4: DUR192LSF(x1) | C4: 888.98305 | D4: PROMOCIONES
A5: DUC101RF01-3.0 | B5: DUC101RF01(x1) | C5: 846.61017 | D5: PROMOCIONES
A6: DUC101Z01-6.0 | B6: DUC101Z01(x1) + 632F69-8(x1) + 630718-5(x1) | C6: 973.72881 | D6: PROMOCIONES
A7: DUC254Z-3.0 | B7: DUC254Z(x1) + 632G12-3(x1) + 630718-5(x1) | C7: 1185.5932 | D7: PROMOCIONES
A8: DUC254Z-6.0 | B8: DUC254Z(x1) + 632F69-8(x1) + 630718-5(x1) | C8: 1312.7119 | D8: PROMOCIONES
A9: DUC407ZX3-3.0 | B9: DUC407ZX3(x1) + 632G12-3(x1) + 630718-5(x1) | C9: 1143.2203 | D9: PROMOCIONES
A10: DUC407ZX3-6.0 | B10: DUC407ZX3(x1) + 632F69-8(x1) + 630718-5(x1) | C10: 1270.339 | D10: PROMOCIONES
A11: DUH606Z-3.0 | B11: DUH606Z(x1) + 632G12-3(x1) + 630718-5(x1) | C11: 1100.8475 | D11: PROMOCIONES
A12: DUH606Z-6.0 | B12: DUH606Z(x1) + 632F69-8(x1) + 630718-5(x1) | C12: 1227.9661 | D12: PROMOCIONES
A13: DUN461WZ-3.0 | B13: DUN461WZ(x1) + 632G12-3(x1) + 630718-5(x1) | C13: 829.66102 | D13: PROMOCIONES
A14: DUN461WZ-6.0 | B14: DUN461WZ(x1) + 632F69-8(x1) + 630718-5(x1) | C14: 1016.1017 | D14: PROMOCIONES
... A56: DUV320Z-6.0 | B56: DUV320Z(x1) + 632F69-8(x1) + 630718-5(x1) | C56: 1312.7119 | D56: PROMOCIONES
A57: CL117FDX1-B | B57: CL117FDX1(x1) | C57: 338.14 | D57: PROMOCIONES | F57: BIRUMEN LISTA 2
A58: CL117FDX4-B | B58: CL117FDX4(x1) | C58: 338.14 | D58: PROMOCIONES
A59: CL117FDX7-B | B59: CL117FDX7(x1) | C59: 338.14 | D59: PROMOCIONES
A60: CL108FDZW-2.0 | B60: CL108FDZW(x1) + 632F59-1(x1) + 630996-7(x1) | C60: 422.88 | D60: PROMOCIONES
A61: DCL181FZW-3.0 | B61: DCL181FZW(x1) + 632G12-3(x1) + 630718-5(x1) | C61: 507.63 | D61: PROMOCIONES
A62: DCL181FZW-6.0 | B62: DCL181FZW(x1) + 632F69-8(x1) + 630718-5(x1) | C62: 592.37 | D62: PROMOCIONES
A63: DCL283FZB-3.0 | B63: DCL283FZB(x1) + 632G12-3(x1) + 630718-5(x1) | C63: 634.75 | D63: PROMOCIONES
A64: DCL283FZB-6.0 | B64: DCL283FZB(x1) + 632F69-8(x1) + 630718-5(x1) | C64: 719.49 | D64: PROMOCIONES
A65: DCL283FZW-3.0 | B65: DCL283FZW(x1) + 632G12-3(x1) + 630718-5(x1) | C65: 634.75 | D65: PROMOCIONES
A66: DCL283FZW-6.0 | B66: DCL283FZW(x1) + 632F69-8(x1) + 630718-5(x1) | C66: 719.49 | D66: PROMOCIONES
A67: DCL286FZB-3.0 | B67: DCL286FZB(x1) + 632G12-3(x1) + 630718-5(x1) | C67: 677.12 | D67: PROMOCIONES
A68: DCL286FZB-6.0 | B68: DCL286FZB(x1) + 632F69-8(x1) + 630718-5(x1) | C68: 761.86 | D68: PROMOCIONES
A69: DCL286FZW-3.0 | B69: DCL286FZW(x1) + 632G12-3(x1) + 630718-5(x1) | C69: 677.12 | D69: PROMOCIONES
... A109: PS001GZ-4.0F | B109: PS001GZ(x1) + 632T21-0(x1) + 630B63-0(x1) | C109: 2795.76 | D109: PROMOCIONES
A110: LM004GZ-5.0 | B110: LM004GZ(x1) + 632R45-4(x1) + 630B63-0(x1) | C110: 2202.5424 | D110: PROMOCIONES | F110: XGT LISTA 2
A111: LM004GZ-8.0 | B111: LM004GZ(x1) + 632S90-5(x1) + 630B63-0(x1) | C111: 2456.7797 | D111: PROMOCIONES
A112: LM002GZ-5.0 | B112: LM002GZ(x1) + 632R45-4(x2) + 630C46-6(x1) | C112: 5083.8983 | D112: PROMOCIONES
A113: LM002GZ-8.0 | B113: LM002GZ(x1) + 632S90-5(x2) + 630C46-6(x1) | C113: 5507.6271 | D113: PROMOCIONES
A114: UR002GZ-5.0 | B114: UR002GZ(x1) + 632R45-4(x1) + 630B63-0(x1) | C114: 2202.5424 | D114: PROMOCIONES
A115: UR002GZ-8.0 | B115: UR002GZ(x1) + 632S90-5(x1) + 630B63-0(x1) | C115: 2456.7797 | D115: PROMOCIONES
A116: UR016GZ-5.0 | B116: UR016GZ(x1) + 632R45-4(x1) + 630B63-0(x1) | C116: 2287.2881 | D116: PROMOCIONES
A117: UR016GZ-8.0 | B117: UR016GZ(x1) + 632S90-5(x1) + 630B63-0(x1) | C117: 2541.5254 | D117: PROMOCIONES
A118: UR006GZ02-5.0 | B118: UR006GZ02(x1) + 632R45-4(x1) + 630B63-0(x1) | C118: 2372.0339 | D118: PROMOCIONES
A119: UR006GZ02-8.0 | B119: UR006GZ02(x1) + 632S90-5(x1) + 630B63-0(x1) | C119: 2626.2712 | D119: PROMOCIONES
A120: UR013GZ03-5.0 | B120: UR013GZ03(x1) + 632R45-4(x1) + 630B63-0(x1) | C120: 2795.7627 | D120: PROMOCIONES
A121: UR013GZ03-8.0 | B121: UR013GZ03(x1) + 632S90-5(x1) + 630B63-0(x1) | C121: 3050 | D121: PROMOCIONES
A122: UR012GZ02-5.0 | B122: UR012GZ02(x1) + 632R45-4(x2) + 630C46-6(x1) | C122: 3812.7119 | D122: PROMOCIONES
... A153: UV001GZ-8.0 | B153: UV001GZ(x1) + 632S90-5(x2) + 630C46-6(x1) | C153: 4236.4407 | D153: PROMOCIONES
A154: E-13611-50 | B154: E-13611(x1) | C154: 257.52742 | D154: PROMOCIONES | F154: OPE ACC LISTA 2
A155: E-13633-80 | B155: E-13633(x1) | C155: 278.46461 | D155: PROMOCIONES
A156: E-07294-100 | B156: E-07294(x1) | C156: 292.42273 | D156: PROMOCIONES
A157: E-07303-150 | B157: E-07303(x1) | C157: 327.31805 | D157: PROMOCIONES
A158: E-07319-200 | B158: E-07319(x1) | C158: 383.15055 | D158: PROMOCIONES
A159: E-07325-X | B159: E-07325(x1) | C159: 90.02991 | D159: PROMOCIONES
A160: 195922-8-OPE | B160: 195922-8(x1) | C160: 348.25523 | D160: PROMOCIONES
A161: 198761-5-OPE | B161: 198761-5(x1) | C161: 348.25523 | D161: PROMOCIONES
A162: 191M57-1-OPE | B162: 191M57-1(x1) | C162: 1185.7428 | D162: PROMOCIONES
A163: 191N34-9-OPE | B163: 191N34-9(x1) | C163: 278.46461 | D163: PROMOCIONES
A164: 191N46-2-OPE | B164: 191N46-2(x1) | C164: 278.46461 | D164: PROMOCIONES
A165: 196751-2-OPE | B165: 196751-2(x1) | C165: 383.15055 | D165: PROMOCIONES
A166: 191F68-4-OPE | B166: 191F68-4(x1) | C166: 452.94118 | D166: PROMOCIONES
... A187: DCL181FZW-MP4 | B187: DCL181FZW(x1) + DLX2283S(x1) | C187: 838.22034 | D187: PROMOCIONES
A188: CO-DHP489RFJ-1225 | B188: DHP489RFJ(x1)+ D-74887(x1) | C188: 761.86
A189: CO-DLX2283S-1225 | B189: DLX2283S(x2)+ D-20719(x2)+ E-15768(x2) | C189: 1516.95
A190: CO-DTW1001RTJ-1225 | B190: DTW1001RTJ(x1)+ T-04282(x1) | C190: 1439.83
A191: CO-DGA458RTJ-1225 | B191: DGA458RTJ(x1)+ D-72001(x20)+ Z71296-1(x1) | C191: 930.51
A192: CO-DMP181Z-1225 | B192: DMP181Z(x1)+ 632M83-6(x1)+ P0114(x1)+ 630718-5(x1) | C192: 575.42
A193: PR-DMR203-1225 | B193: DMR203(x2) | C193: 804.24
A194: CO-DHR171Z-1225 | B194: DHR171Z(x1)+ 632F15-1(x1)+ 630718-5(x1) | C194: 634.75
A195: CO-DHP490WVX-1225 | B195: DHP490WVX(x1)+ D-20719(x1) | C195: 338.14
A196: CO-DLS211Z-1125 | B196: DLS211Z(x1)+ 1915J2-8(x2)+ 196933-6(x1) | C196: 3134.75
A197: CO-DSL801Z-1125 | B197: DSL801Z(x1)+ 1915H4-0(x2)+ 630718-5(x1) | C197: 1778.81
A198: CO-DTD173Z-1225 | B198: DTD173Z(x1)+ 632G12-3(x1)+ 630D27-6(x1) | C198: 507.63
A199: CO-DRT50Z-1125 | B199: DRT50Z(x1)+ DBO481Z(x1)+ 632U33-9(x2)+ 630D27-6(x1) | C199: 1185.59
... A324: DCL181FZW-3.0E | B324: DCL181FZW(x1) + 632G12-3(x1) + 630718-5(x1) | C324: 447.90628

Sheet Lista de Productos
A1: COD. ARTICULO | B1: DESCRIPCION | C1: FAMILIA SAP | D1: Status | E1: LISTA GENERAL
A2: 042040-2A | B2: PAQUETE DE GRASA 500 G. PARA MODELOS HR52 | C2: ACCESORIOS | D2: Verde | E2: 110.3
A3: 103154900 | B3: WIDE REFLECTOR NOZZLE 75MM | C3: ACCESORIOS | D3: Morado | E3: 34.17
A4: 103155000 | B4: WIDE REFLECTOR NOZZLE PB | C4: ACCESORIOS | D4: Morado | E4: 50.47
A5: 103155100 | B5: BOQUILLA DE REDUCCION 9mm | C5: ACCESORIOS | D5: Amarillo | E5: 29.4
A6: 110751-A | B6: ""BOQUILLA 1.3/4""x 3/16"" PVC" | C6: ACCESORIOS | D6: Morado | E6: 122.34
A7: 122256-6 | B7: PORTA GUIA CIRCULAR 3612-BR | C7: ACCESORIOS | D7: Rojo | E7: 113.4
A8: 122291-4 | B8: Boquilla Tipo T para Alfombra (Crema) | C8: ACCESORIOS | D8: Rojo | E8: 69.3
A9: 122296-4 | B9: BOLSA PARA POLVO P/9924DB | C9: ACCESORIOS | D9: Amarillo | E9: 71.25
A10: 122321-1 | B10: BOLSA PARA POLVO P/4014N | C10: ACCESORIOS | D10: Rojo | E10: 11.24
A11: 122335-0 | B11: Boquilla Tipo T Húmedo Marfil (38 mm) | C11: ACCESORIOS | D11: Morado | E11: 82.47
A12: 122343-1 | B12: GUIA RECORTADORA P/3606 | C12: ACCESORIOS | D12: Morado | E12: 134.82
A13: 122402-1 | B13: BOLSA PARA POLVO | C13: ACCESORIOS | D13: Amarillo | E13: 196.61
... A5838: ZM00000228 | B5838: ACCESORIO PARA CRIMPADORA DTC301/302 MEDIDA CABLE K34 | C5838: ACCESORIOS | D5838: Morado | E5838: 1267.28
A5839: LM004GZ-5.0X | B5839: LM004GZ(x1) + 632X12-5(x1) + 630B63-0(x1) | C5839: PROMOCIONES | E5839: 2202.5424
A5840: LM004GZ-8.0X | B5840: LM004GZ(x1) + 632X21-4(x1) + 630B63-0(x1) | C5840: PROMOCIONES | E5840: 2456.7797
A5841: LM002GZ-5.0X | B5841: LM002GZ(x1) + 632X12-5(x2) + 630C46-6(x1) | C5841: PROMOCIONES | E5841: 5083.8983
A5842: LM002GZ-8.0X | B5842: LM002GZ(x1) + 632X21-4(x2) + 630C46-6(x1) | C5842: PROMOCIONES | E5842: 5507.6271
A5843: UR002GZ-5.0X | B5843: UR002GZ(x1) + 632X12-5(x1) + 630B63-0(x1) | C5843: PROMOCIONES | E5843: 2202.5424
A5844: UR002GZ-8.0X | B5844: UR002GZ(x1) + 632X21-4(x1) + 630B63-0(x1) | C5844: PROMOCIONES | E5844: 2456.7797
A5845: UR016GZ-5.0X | B5845: UR016GZ(x1) + 632X12-5(x1) + 630B63-0(x1) | C5845: PROMOCIONES | E5845: 2287.2881
A5846: UR006GZ02-5.0X | B5846: UR006GZ02(x1) + 632X12-5(x1) + 630B63-0(x1) | C5846: PROMOCIONES | E5846: 2372.0339
A5847: UR006GZ02-8.0X | B5847: UR006GZ02(x1) + 632X21-4(x1) + 630B63-0(x1) | C5847: PROMOCIONES | E5847: 2626.2712
A5848: UR013GZ03-5.0X | B5848: UR013GZ03(x1) + 632X12-5(x1) + 630B63-0(x1) | C5848: PROMOCIONES | E5848: 2795.7627
A5849: UR013GZ03-8.0X | B5849: UR013GZ03(x1) + 632X21-4(x1) + 630B63-0(x1) | C5849: PROMOCIONES | E5849: 3050
A5850: UR012GZ02-8.0X | B5850: UR012GZ02(x1) + 632X21-4(x2) + 630C46-6(x1) | C5850: PROMOCIONES | E5850: 4236.4407
... A6172: VC013GLZ-LQ2 | B6172: VC013GLZ(x1) + BO003CGZ(x1) + 632X12-5(x1)+ 630C66-0(x1) | C6172: PROMOCIONES | E6172: 1677.2034
